{"ride_id":1,"driver_id":1038,"distance_km":3.6621729086,"fare_usd":45.4342367864,"ride_type":"standard","city":"Berlin","timestamp":"2025-01-01T00:00:00.000"}
{"ride_id":2,"driver_id":1028,"distance_km":3.7305526598,"fare_usd":16.58593222,"ride_type":"pool","city":"Seoul","timestamp":"2025-01-01T00:01:00.000"}
{"ride_id":3,"driver_id":1014,"distance_km":10.0309859723,"fare_usd":7.3715412173,"ride_type":"pool","city":"Seoul","timestamp":"2025-01-01T00:02:00.000"}
{"ride_id":4,"driver_id":1042,"distance_km":29.40580533,"fare_usd":26.8031219793,"ride_type":"premium","city":"Lima","timestamp":"2025-01-01T00:03:00.000"}
{"ride_id":5,"driver_id":1007,"distance_km":6.0845778268,"fare_usd":59.6346995282,"ride_type":"pool","city":"Nairobi","timestamp":"2025-01-01T00:04:00.000"}
{"ride_id":6,"driver_id":1020,"distance_km":1.4976719531,"fare_usd":24.4311020841,"ride_type":"pool","city":"Seoul","timestamp":"2025-01-01T00:05:00.000"}
{"ride_id":7,"driver_id":1038,"distance_km":23.1375682671,"fare_usd":20.4068049857,"ride_type":"standard","city":"Nairobi","timestamp":"2025-01-01T00:06:00.000"}
{"ride_id":8,"driver_id":1018,"distance_km":24.4004763345,"fare_usd":19.8876549039,"ride_type":"standard","city":"Toronto","timestamp":"2025-01-01T00:07:00.000"}
{"ride_id":9,"driver_id":1022,"distance_km":11.0428253116,"fare_usd":41.0621577685,"ride_type":"premium","city":"Berlin","timestamp":"2025-01-01T00:08:00.000"}
{"ride_id":10,"driver_id":1010,"distance_km":14.4755405752,"fare_usd":73.2878920978,"ride_type":"pool","city":"Lima","timestamp":"2025-01-01T00:09:00.000"}
{"ride_id":11,"driver_id":1010,"distance_km":19.8434367966,"fare_usd":37.1292291612,"ride_type":"pool","city":"Nairobi","timestamp":"2025-01-01T00:10:00.000"}
{"ride_id":12,"driver_id":1023,"distance_km":2.3937088017,"fare_usd":44.0113758223,"ride_type":"standard","city":"Seoul","timestamp":"2025-01-01T00:11:00.000"}
{"ride_id":13,"driver_id":1035,"distance_km":28.5252262162,"fare_usd":65.2442412524,"ride_type":"pool","city":"Nairobi","timestamp":"2025-01-01T00:12:00.000"}
{"ride_id":14,"driver_id":1039,"distance_km":26.7137312316,"fare_usd":42.4548803254,"ride_type":"standard","city":"Seoul","timestamp":"2025-01-01T00:13:00.000"}
{"ride_id":15,"driver_id":1023,"distance_km":8.5659150769,"fare_usd":17.9124009993,"ride_type":"premium","city":"Nairobi","timestamp":"2025-01-01T00:14:00.000"}
{"ride_id":16,"driver_id":1002,"distance_km":1.4438316684,"fare_usd":25.9717138237,"ride_type":"standard","city":"Seoul","timestamp":"2025-01-01T00:15:00.000"}
{"ride_id":17,"driver_id":1021,"distance_km":28.0696529343,"fare_usd":26.6955848388,"ride_type":"pool","city":"Toronto","timestamp":"2025-01-01T00:16:00.000"}
{"ride_id":18,"driver_id":1001,"distance_km":15.5301566335,"fare_usd":32.812268082,"ride_type":"premium","city":"Seoul","timestamp":"2025-01-01T00:17:00.000"}
{"ride_id":19,"driver_id":1023,"distance_km":16.6419460036,"fare_usd":34.8752233736,"ride_type":"standard","city":"Seoul","timestamp":"2025-01-01T00:18:00.000"}
{"ride_id":20,"driver_id":1043,"distance_km":20.8349493125,"fare_usd":60.9847415452,"ride_type":"standard","city":"Berlin","timestamp":"2025-01-01T00:19:00.000"}
{"ride_id":21,"driver_id":1029,"distance_km":18.8596837673,"fare_usd":29.4570899335,"ride_type":"premium","city":"Seoul","timestamp":"2025-01-01T00:20:00.000"}
{"ride_id":22,"driver_id":1037,"distance_km":28.3728565323,"fare_usd":37.7762279909,"ride_type":"premium","city":"Berlin","timestamp":"2025-01-01T00:21:00.000"}
{"ride_id":23,"driver_id":1001,"distance_km":28.3832963166,"fare_usd":48.7483190936,"ride_type":"standard","city":"Lima","timestamp":"2025-01-01T00:22:00.000"}
{"ride_id":24,"driver_id":1020,"distance_km":26.1487690731,"fare_usd":31.4408163208,"ride_type":"pool","city":"Berlin","timestamp":"2025-01-01T00:23:00.000"}
{"ride_id":25,"driver_id":1032,"distance_km":19.4557043259,"fare_usd":63.5595369305,"ride_type":"standard","city":"Toronto","timestamp":"2025-01-01T00:24:00.000"}
{"ride_id":26,"driver_id":1011,"distance_km":24.2275295458,"fare_usd":46.1217522964,"ride_type":"premium","city":"Berlin","timestamp":"2025-01-01T00:25:00.000"}
{"ride_id":27,"driver_id":1021,"distance_km":20.6378819291,"fare_usd":25.5831275455,"ride_type":"standard","city":"Lima","timestamp":"2025-01-01T00:26:00.000"}
{"ride_id":28,"driver_id":1043,"distance_km":17.6276442085,"fare_usd":54.9841439853,"ride_type":"premium","city":"Toronto","timestamp":"2025-01-01T00:27:00.000"}
{"ride_id":29,"driver_id":1024,"distance_km":4.7265102438,"fare_usd":41.9353411101,"ride_type":"premium","city":"Nairobi","timestamp":"2025-01-01T00:28:00.000"}
{"ride_id":30,"driver_id":1048,"distance_km":24.5249211253,"fare_usd":42.411912388,"ride_type":"pool","city":"Nairobi","timestamp":"2025-01-01T00:29:00.000"}
{"ride_id":31,"driver_id":1026,"distance_km":24.7985447966,"fare_usd":38.6761563871,"ride_type":"premium","city":"Berlin","timestamp":"2025-01-01T00:30:00.000"}
{"ride_id":32,"driver_id":1041,"distance_km":19.1522504329,"fare_usd":39.7908364175,"ride_type":"premium","city":"Berlin","timestamp":"2025-01-01T00:31:00.000"}
{"ride_id":33,"driver_id":1027,"distance_km":24.7923784694,"fare_usd":58.5749396746,"ride_type":"pool","city":"Lima","timestamp":"2025-01-01T00:32:00.000"}
{"ride_id":34,"driver_id":1015,"distance_km":19.8930583839,"fare_usd":12.2087035532,"ride_type":"premium","city":"Lima","timestamp":"2025-01-01T00:33:00.000"}
{"ride_id":35,"driver_id":1014,"distance_km":6.9938464364,"fare_usd":28.4053967917,"ride_type":"pool","city":"Seoul","timestamp":"2025-01-01T00:34:00.000"}
{"ride_id":36,"driver_id":1046,"distance_km":8.9448726923,"fare_usd":10.2852354663,"ride_type":"pool","city":"Lima","timestamp":"2025-01-01T00:35:00.000"}
{"ride_id":37,"driver_id":1050,"distance_km":7.2230844715,"fare_usd":57.7272354523,"ride_type":"premium","city":"Seoul","timestamp":"2025-01-01T00:36:00.000"}
{"ride_id":38,"driver_id":1043,"distance_km":11.9405134136,"fare_usd":24.0611298304,"ride_type":"premium","city":"Toronto","timestamp":"2025-01-01T00:37:00.000"}
{"ride_id":39,"driver_id":1002,"distance_km":2.129930837,"fare_usd":67.8201286873,"ride_type":"standard","city":"Berlin","timestamp":"2025-01-01T00:38:00.000"}
{"ride_id":40,"driver_id":1036,"distance_km":18.9293626458,"fare_usd":41.8604926662,"ride_type":"pool","city":"Toronto","timestamp":"2025-01-01T00:39:00.000"}
{"ride_id":41,"driver_id":1050,"distance_km":10.7600722318,"fare_usd":61.052484004,"ride_type":"standard","city":"Lima","timestamp":"2025-01-01T00:40:00.000"}
{"ride_id":42,"driver_id":1006,"distance_km":20.015956426,"fare_usd":73.5252004931,"ride_type":"premium","city":"Toronto","timestamp":"2025-01-01T00:41:00.000"}
{"ride_id":43,"driver_id":1020,"distance_km":12.176502008,"fare_usd":63.785220162,"ride_type":"standard","city":"Toronto","timestamp":"2025-01-01T00:42:00.000"}
{"ride_id":44,"driver_id":1008,"distance_km":20.7667964002,"fare_usd":65.6895632008,"ride_type":"pool","city":"Toronto","timestamp":"2025-01-01T00:43:00.000"}
{"ride_id":45,"driver_id":1038,"distance_km":10.8781125145,"fare_usd":33.5589146755,"ride_type":"standard","city":"Lima","timestamp":"2025-01-01T00:44:00.000"}
{"ride_id":46,"driver_id":1017,"distance_km":8.5601413188,"fare_usd":43.6205816682,"ride_type":"pool","city":"Toronto","timestamp":"2025-01-01T00:45:00.000"}
{"ride_id":47,"driver_id":1003,"distance_km":15.3850861745,"fare_usd":22.772199483,"ride_type":"premium","city":"Seoul","timestamp":"2025-01-01T00:46:00.000"}
{"ride_id":48,"driver_id":1024,"distance_km":21.0938204021,"fare_usd":18.7279169785,"ride_type":"premium","city":"Lima","timestamp":"2025-01-01T00:47:00.000"}
{"ride_id":49,"driver_id":1013,"distance_km":11.1017615291,"fare_usd":40.3855515374,"ride_type":"pool","city":"Toronto","timestamp":"2025-01-01T00:48:00.000"}
{"ride_id":50,"driver_id":1049,"distance_km":28.1627964038,"fare_usd":46.653428579,"ride_type":"premium","city":"Lima","timestamp":"2025-01-01T00:49:00.000"}
{"ride_id":51,"driver_id":1008,"distance_km":2.1364034736,"fare_usd":28.7489872127,"ride_type":"premium","city":"Nairobi","timestamp":"2025-01-01T00:50:00.000"}
{"ride_id":52,"driver_id":1025,"distance_km":13.1204349198,"fare_usd":44.8610462434,"ride_type":"premium","city":"Seoul","timestamp":"2025-01-01T00:51:00.000"}
{"ride_id":53,"driver_id":1001,"distance_km":29.0598359941,"fare_usd":67.1222337759,"ride_type":"premium","city":"Toronto","timestamp":"2025-01-01T00:52:00.000"}
{"ride_id":54,"driver_id":1019,"distance_km":16.8911846142,"fare_usd":43.9705109348,"ride_type":"pool","city":"Nairobi","timestamp":"2025-01-01T00:53:00.000"}
{"ride_id":55,"driver_id":1027,"distance_km":13.2806573269,"fare_usd":55.4569167417,"ride_type":"standard","city":"Nairobi","timestamp":"2025-01-01T00:54:00.000"}
{"ride_id":56,"driver_id":1046,"distance_km":17.4870882287,"fare_usd":61.3720477151,"ride_type":"standard","city":"Lima","timestamp":"2025-01-01T00:55:00.000"}
{"ride_id":57,"driver_id":1006,"distance_km":17.7018126825,"fare_usd":74.2110147369,"ride_type":"premium","city":"Nairobi","timestamp":"2025-01-01T00:56:00.000"}
{"ride_id":58,"driver_id":1043,"distance_km":22.2177849037,"fare_usd":47.2238181524,"ride_type":"standard","city":"Seoul","timestamp":"2025-01-01T00:57:00.000"}
{"ride_id":59,"driver_id":1007,"distance_km":4.7030021533,"fare_usd":61.4795104274,"ride_type":"standard","city":"Seoul","timestamp":"2025-01-01T00:58:00.000"}
{"ride_id":60,"driver_id":1046,"distance_km":8.2504770273,"fare_usd":72.3854522988,"ride_type":"premium","city":"Berlin","timestamp":"2025-01-01T00:59:00.000"}
{"ride_id":61,"driver_id":1034,"distance_km":17.835776358,"fare_usd":71.1086807904,"ride_type":"premium","city":"Seoul","timestamp":"2025-01-01T01:00:00.000"}
{"ride_id":62,"driver_id":1013,"distance_km":26.1463816091,"fare_usd":14.8757294144,"ride_type":"standard","city":"Nairobi","timestamp":"2025-01-01T01:01:00.000"}
{"ride_id":63,"driver_id":1016,"distance_km":17.2941340722,"fare_usd":33.4474615791,"ride_type":"pool","city":"Seoul","timestamp":"2025-01-01T01:02:00.000"}
{"ride_id":64,"driver_id":1035,"distance_km":7.9193089339,"fare_usd":27.6793042775,"ride_type":"premium","city":"Lima","timestamp":"2025-01-01T01:03:00.000"}
{"ride_id":65,"driver_id":1049,"distance_km":20.7154986171,"fare_usd":11.0847510465,"ride_type":"pool","city":"Berlin","timestamp":"2025-01-01T01:04:00.000"}
{"ride_id":66,"driver_id":1039,"distance_km":22.457354053,"fare_usd":49.3268542438,"ride_type":"standard","city":"Nairobi","timestamp":"2025-01-01T01:05:00.000"}
{"ride_id":67,"driver_id":1003,"distance_km":7.9088484197,"fare_usd":56.5133229237,"ride_type":"premium","city":"Berlin","timestamp":"2025-01-01T01:06:00.000"}
{"ride_id":68,"driver_id":1001,"distance_km":11.9541376991,"fare_usd":64.3689666827,"ride_type":"pool","city":"Nairobi","timestamp":"2025-01-01T01:07:00.000"}
{"ride_id":69,"driver_id":1005,"distance_km":16.4954967324,"fare_usd":13.5943822764,"ride_type":"premium","city":"Lima","timestamp":"2025-01-01T01:08:00.000"}
{"ride_id":70,"driver_id":1041,"distance_km":15.4002745298,"fare_usd":66.3510853113,"ride_type":"standard","city":"Berlin","timestamp":"2025-01-01T01:09:00.000"}
{"ride_id":71,"driver_id":1003,"distance_km":12.2989245004,"fare_usd":50.004789453,"ride_type":"pool","city":"Toronto","timestamp":"2025-01-01T01:10:00.000"}
{"ride_id":72,"driver_id":1028,"distance_km":9.6314200608,"fare_usd":54.2762294597,"ride_type":"standard","city":"Nairobi","timestamp":"2025-01-01T01:11:00.000"}
{"ride_id":73,"driver_id":1017,"distance_km":3.8995617277,"fare_usd":68.7436802478,"ride_type":"standard","city":"Toronto","timestamp":"2025-01-01T01:12:00.000"}
{"ride_id":74,"driver_id":1025,"distance_km":2.5510736057,"fare_usd":48.733288973,"ride_type":"premium","city":"Berlin","timestamp":"2025-01-01T01:13:00.000"}
{"ride_id":75,"driver_id":1043,"distance_km":28.7977034096,"fare_usd":28.5106100005,"ride_type":"pool","city":"Toronto","timestamp":"2025-01-01T01:14:00.000"}
{"ride_id":76,"driver_id":1033,"distance_km":25.5671511788,"fare_usd":62.7575131996,"ride_type":"standard","city":"Toronto","timestamp":"2025-01-01T01:15:00.000"}
{"ride_id":77,"driver_id":1009,"distance_km":11.2922505234,"fare_usd":30.4141448537,"ride_type":"standard","city":"Berlin","timestamp":"2025-01-01T01:16:00.000"}
{"ride_id":78,"driver_id":1035,"distance_km":28.7472256687,"fare_usd":7.3959677574,"ride_type":"pool","city":"Lima","timestamp":"2025-01-01T01:17:00.000"}
{"ride_id":79,"driver_id":1013,"distance_km":20.6263272283,"fare_usd":63.1458154596,"ride_type":"standard","city":"Toronto","timestamp":"2025-01-01T01:18:00.000"}
{"ride_id":80,"driver_id":1030,"distance_km":14.9931075396,"fare_usd":29.1634501417,"ride_type":"standard","city":"Toronto","timestamp":"2025-01-01T01:19:00.000"}
{"ride_id":81,"driver_id":1047,"distance_km":15.2977440754,"fare_usd":59.1684166241,"ride_type":"pool","city":"Lima","timestamp":"2025-01-01T01:20:00.000"}
{"ride_id":82,"driver_id":1014,"distance_km":3.4152479247,"fare_usd":30.3930526266,"ride_type":"pool","city":"Toronto","timestamp":"2025-01-01T01:21:00.000"}
{"ride_id":83,"driver_id":1007,"distance_km":3.6594202705,"fare_usd":65.2747613982,"ride_type":"pool","city":"Toronto","timestamp":"2025-01-01T01:22:00.000"}
{"ride_id":84,"driver_id":1013,"distance_km":18.4707868511,"fare_usd":20.3657367557,"ride_type":"pool","city":"Toronto","timestamp":"2025-01-01T01:23:00.000"}
{"ride_id":85,"driver_id":1022,"distance_km":17.057388518,"fare_usd":73.2183085639,"ride_type":"premium","city":"Seoul","timestamp":"2025-01-01T01:24:00.000"}
{"ride_id":86,"driver_id":1039,"distance_km":7.1691089557,"fare_usd":59.5831142352,"ride_type":"pool","city":"Lima","timestamp":"2025-01-01T01:25:00.000"}
{"ride_id":87,"driver_id":1020,"distance_km":28.4396417436,"fare_usd":12.9966548144,"ride_type":"premium","city":"Toronto","timestamp":"2025-01-01T01:26:00.000"}
{"ride_id":88,"driver_id":1015,"distance_km":23.6575854637,"fare_usd":44.6043633977,"ride_type":"premium","city":"Lima","timestamp":"2025-01-01T01:27:00.000"}
{"ride_id":89,"driver_id":1044,"distance_km":4.2904734585,"fare_usd":73.9757118569,"ride_type":"premium","city":"Nairobi","timestamp":"2025-01-01T01:28:00.000"}
{"ride_id":90,"driver_id":1017,"distance_km":27.9969440649,"fare_usd":37.9745816886,"ride_type":"standard","city":"Nairobi","timestamp":"2025-01-01T01:29:00.000"}
{"ride_id":91,"driver_id":1046,"distance_km":29.2531980475,"fare_usd":17.7474997175,"ride_type":"premium","city":"Toronto","timestamp":"2025-01-01T01:30:00.000"}
{"ride_id":92,"driver_id":1023,"distance_km":29.8820060189,"fare_usd":38.9344857005,"ride_type":"premium","city":"Lima","timestamp":"2025-01-01T01:31:00.000"}
{"ride_id":93,"driver_id":1025,"distance_km":2.6202634856,"fare_usd":40.8720359117,"ride_type":"standard","city":"Lima","timestamp":"2025-01-01T01:32:00.000"}
{"ride_id":94,"driver_id":1024,"distance_km":22.3740311469,"fare_usd":56.918086096,"ride_type":"standard","city":"Lima","timestamp":"2025-01-01T01:33:00.000"}
{"ride_id":95,"driver_id":1044,"distance_km":16.8315573348,"fare_usd":53.9192097213,"ride_type":"standard","city":"Seoul","timestamp":"2025-01-01T01:34:00.000"}
{"ride_id":96,"driver_id":1040,"distance_km":21.4691130325,"fare_usd":33.1785030518,"ride_type":"pool","city":"Nairobi","timestamp":"2025-01-01T01:35:00.000"}
{"ride_id":97,"driver_id":1028,"distance_km":29.0909063752,"fare_usd":20.2616175246,"ride_type":"standard","city":"Lima","timestamp":"2025-01-01T01:36:00.000"}
{"ride_id":98,"driver_id":1014,"distance_km":20.9528702951,"fare_usd":50.1537917439,"ride_type":"standard","city":"Lima","timestamp":"2025-01-01T01:37:00.000"}
{"ride_id":99,"driver_id":1044,"distance_km":25.2719523529,"fare_usd":34.5192754187,"ride_type":"premium","city":"Seoul","timestamp":"2025-01-01T01:38:00.000"}
{"ride_id":100,"driver_id":1000,"distance_km":26.139192454,"fare_usd":14.2593347788,"ride_type":"standard","city":"Seoul","timestamp":"2025-01-01T01:39:00.000"}
{"ride_id":101,"driver_id":1024,"distance_km":25.3159421492,"fare_usd":68.0400610865,"ride_type":"pool","city":"Lima","timestamp":"2025-01-01T01:40:00.000"}
{"ride_id":102,"driver_id":1006,"distance_km":13.3566527764,"fare_usd":53.3855300327,"ride_type":"standard","city":"Berlin","timestamp":"2025-01-01T01:41:00.000"}
{"ride_id":103,"driver_id":1008,"distance_km":7.4547161096,"fare_usd":52.8228699512,"ride_type":"pool","city":"Lima","timestamp":"2025-01-01T01:42:00.000"}
{"ride_id":104,"driver_id":1023,"distance_km":12.5028964567,"fare_usd":62.5808713138,"ride_type":"standard","city":"Lima","timestamp":"2025-01-01T01:43:00.000"}
{"ride_id":105,"driver_id":1000,"distance_km":26.8650103545,"fare_usd":42.0763175059,"ride_type":"standard","city":"Seoul","timestamp":"2025-01-01T01:44:00.000"}
{"ride_id":106,"driver_id":1043,"distance_km":5.2515398291,"fare_usd":62.0538099882,"ride_type":"standard","city":"Seoul","timestamp":"2025-01-01T01:45:00.000"}
{"ride_id":107,"driver_id":1007,"distance_km":15.8864588921,"fare_usd":39.8663527458,"ride_type":"standard","city":"Lima","timestamp":"2025-01-01T01:46:00.000"}
{"ride_id":108,"driver_id":1023,"distance_km":7.7636141003,"fare_usd":9.7022779941,"ride_type":"pool","city":"Lima","timestamp":"2025-01-01T01:47:00.000"}
{"ride_id":109,"driver_id":1010,"distance_km":17.8578570996,"fare_usd":33.3673661619,"ride_type":"pool","city":"Lima","timestamp":"2025-01-01T01:48:00.000"}
{"ride_id":110,"driver_id":1050,"distance_km":26.0310171377,"fare_usd":39.8225425786,"ride_type":"premium","city":"Seoul","timestamp":"2025-01-01T01:49:00.000"}
{"ride_id":111,"driver_id":1016,"distance_km":26.5304390905,"fare_usd":55.4141807143,"ride_type":"pool","city":"Lima","timestamp":"2025-01-01T01:50:00.000"}
{"ride_id":112,"driver_id":1007,"distance_km":7.8638706168,"fare_usd":12.460511109,"ride_type":"standard","city":"Lima","timestamp":"2025-01-01T01:51:00.000"}
{"ride_id":113,"driver_id":1034,"distance_km":27.3231174841,"fare_usd":14.8012977062,"ride_type":"premium","city":"Toronto","timestamp":"2025-01-01T01:52:00.000"}
{"ride_id":114,"driver_id":1034,"distance_km":18.1647734258,"fare_usd":23.4578661844,"ride_type":"premium","city":"Berlin","timestamp":"2025-01-01T01:53:00.000"}
{"ride_id":115,"driver_id":1032,"distance_km":11.1563291543,"fare_usd":23.654887536,"ride_type":"premium","city":"Nairobi","timestamp":"2025-01-01T01:54:00.000"}
{"ride_id":116,"driver_id":1004,"distance_km":21.5372546719,"fare_usd":56.2529204921,"ride_type":"standard","city":"Berlin","timestamp":"2025-01-01T01:55:00.000"}
{"ride_id":117,"driver_id":1041,"distance_km":14.968342651,"fare_usd":22.5511462393,"ride_type":"pool","city":"Toronto","timestamp":"2025-01-01T01:56:00.000"}
{"ride_id":118,"driver_id":1038,"distance_km":11.9616401135,"fare_usd":49.316864435,"ride_type":"standard","city":"Nairobi","timestamp":"2025-01-01T01:57:00.000"}
{"ride_id":119,"driver_id":1040,"distance_km":21.4474465646,"fare_usd":39.5991695097,"ride_type":"premium","city":"Lima","timestamp":"2025-01-01T01:58:00.000"}
{"ride_id":120,"driver_id":1027,"distance_km":8.2130004785,"fare_usd":45.1306064726,"ride_type":"standard","city":"Toronto","timestamp":"2025-01-01T01:59:00.000"}
{"ride_id":121,"driver_id":1006,"distance_km":10.5773233416,"fare_usd":63.6674874225,"ride_type":"standard","city":"Lima","timestamp":"2025-01-01T02:00:00.000"}
{"ride_id":122,"driver_id":1008,"distance_km":13.5991034902,"fare_usd":33.3067051084,"ride_type":"pool","city":"Seoul","timestamp":"2025-01-01T02:01:00.000"}
{"ride_id":123,"driver_id":1007,"distance_km":8.3567830423,"fare_usd":58.9637963945,"ride_type":"pool","city":"Toronto","timestamp":"2025-01-01T02:02:00.000"}
{"ride_id":124,"driver_id":1011,"distance_km":12.7508605167,"fare_usd":34.5425241685,"ride_type":"premium","city":"Seoul","timestamp":"2025-01-01T02:03:00.000"}
{"ride_id":125,"driver_id":1033,"distance_km":17.5727177309,"fare_usd":29.7709963593,"ride_type":"standard","city":"Toronto","timestamp":"2025-01-01T02:04:00.000"}
{"ride_id":126,"driver_id":1032,"distance_km":22.4882419664,"fare_usd":72.1039024119,"ride_type":"standard","city":"Toronto","timestamp":"2025-01-01T02:05:00.000"}
{"ride_id":127,"driver_id":1047,"distance_km":23.2486507401,"fare_usd":17.9059644475,"ride_type":"pool","city":"Seoul","timestamp":"2025-01-01T02:06:00.000"}
{"ride_id":128,"driver_id":1022,"distance_km":24.8609202044,"fare_usd":11.3235872404,"ride_type":"standard","city":"Nairobi","timestamp":"2025-01-01T02:07:00.000"}
{"ride_id":129,"driver_id":1023,"distance_km":22.5821380514,"fare_usd":58.9690147875,"ride_type":"standard","city":"Berlin","timestamp":"2025-01-01T02:08:00.000"}
{"ride_id":130,"driver_id":1036,"distance_km":20.7501433858,"fare_usd":9.7774793748,"ride_type":"standard","city":"Lima","timestamp":"2025-01-01T02:09:00.000"}
{"ride_id":131,"driver_id":1034,"distance_km":7.8876876675,"fare_usd":63.5955293492,"ride_type":"pool","city":"Toronto","timestamp":"2025-01-01T02:10:00.000"}
{"ride_id":132,"driver_id":1043,"distance_km":12.6064638933,"fare_usd":35.603537745,"ride_type":"premium","city":"Lima","timestamp":"2025-01-01T02:11:00.000"}
{"ride_id":133,"driver_id":1039,"distance_km":14.8537318355,"fare_usd":69.0859574104,"ride_type":"premium","city":"Seoul","timestamp":"2025-01-01T02:12:00.000"}
{"ride_id":134,"driver_id":1021,"distance_km":3.4038483291,"fare_usd":55.5073002785,"ride_type":"standard","city":"Lima","timestamp":"2025-01-01T02:13:00.000"}
{"ride_id":135,"driver_id":1026,"distance_km":16.3227335176,"fare_usd":47.7283266906,"ride_type":"premium","city":"Seoul","timestamp":"2025-01-01T02:14:00.000"}
{"ride_id":136,"driver_id":1034,"distance_km":13.6537391166,"fare_usd":71.451475794,"ride_type":"pool","city":"Lima","timestamp":"2025-01-01T02:15:00.000"}
{"ride_id":137,"driver_id":1000,"distance_km":24.2611682218,"fare_usd":32.7654561136,"ride_type":"pool","city":"Berlin","timestamp":"2025-01-01T02:16:00.000"}
{"ride_id":138,"driver_id":1034,"distance_km":29.3591193939,"fare_usd":71.7860855578,"ride_type":"premium","city":"Berlin","timestamp":"2025-01-01T02:17:00.000"}
{"ride_id":139,"driver_id":1036,"distance_km":17.1241461206,"fare_usd":14.4500894195,"ride_type":"premium","city":"Berlin","timestamp":"2025-01-01T02:18:00.000"}
{"ride_id":140,"driver_id":1046,"distance_km":10.35790526,"fare_usd":38.8628459353,"ride_type":"standard","city":"Berlin","timestamp":"2025-01-01T02:19:00.000"}
{"ride_id":141,"driver_id":1013,"distance_km":2.2586227156,"fare_usd":23.8937855675,"ride_type":"premium","city":"Berlin","timestamp":"2025-01-01T02:20:00.000"}
{"ride_id":142,"driver_id":1002,"distance_km":27.8146565765,"fare_usd":42.7889945236,"ride_type":"standard","city":"Berlin","timestamp":"2025-01-01T02:21:00.000"}
{"ride_id":143,"driver_id":1000,"distance_km":27.6543557431,"fare_usd":16.3409714524,"ride_type":"standard","city":"Seoul","timestamp":"2025-01-01T02:22:00.000"}
{"ride_id":144,"driver_id":1004,"distance_km":8.3367148717,"fare_usd":63.9070762217,"ride_type":"pool","city":"Toronto","timestamp":"2025-01-01T02:23:00.000"}
{"ride_id":145,"driver_id":1025,"distance_km":21.1669225701,"fare_usd":64.248549452,"ride_type":"pool","city":"Lima","timestamp":"2025-01-01T02:24:00.000"}
{"ride_id":146,"driver_id":1013,"distance_km":3.1876018656,"fare_usd":71.8665418906,"ride_type":"pool","city":"Berlin","timestamp":"2025-01-01T02:25:00.000"}
{"ride_id":147,"driver_id":1038,"distance_km":5.8202475254,"fare_usd":15.8270498618,"ride_type":"pool","city":"Seoul","timestamp":"2025-01-01T02:26:00.000"}
{"ride_id":148,"driver_id":1026,"distance_km":7.287464091,"fare_usd":48.6332785633,"ride_type":"premium","city":"Seoul","timestamp":"2025-01-01T02:27:00.000"}
{"ride_id":149,"driver_id":1008,"distance_km":9.5403244583,"fare_usd":38.196611609,"ride_type":"pool","city":"Seoul","timestamp":"2025-01-01T02:28:00.000"}
{"ride_id":150,"driver_id":1014,"distance_km":29.8791098759,"fare_usd":29.1068612431,"ride_type":"premium","city":"Toronto","timestamp":"2025-01-01T02:29:00.000"}
{"ride_id":151,"driver_id":1014,"distance_km":21.2108266201,"fare_usd":29.6078112794,"ride_type":"pool","city":"Lima","timestamp":"2025-01-01T02:30:00.000"}
{"ride_id":152,"driver_id":1025,"distance_km":12.14185311,"fare_usd":33.8955485425,"ride_type":"premium","city":"Toronto","timestamp":"2025-01-01T02:31:00.000"}
{"ride_id":153,"driver_id":1041,"distance_km":22.3759204694,"fare_usd":54.3447884782,"ride_type":"standard","city":"Nairobi","timestamp":"2025-01-01T02:32:00.000"}
{"ride_id":154,"driver_id":1012,"distance_km":27.5423759084,"fare_usd":46.8800240788,"ride_type":"premium","city":"Seoul","timestamp":"2025-01-01T02:33:00.000"}
{"ride_id":155,"driver_id":1050,"distance_km":28.8023698148,"fare_usd":37.1777058933,"ride_type":"premium","city":"Nairobi","timestamp":"2025-01-01T02:34:00.000"}
{"ride_id":156,"driver_id":1031,"distance_km":2.678053035,"fare_usd":10.3153387259,"ride_type":"pool","city":"Berlin","timestamp":"2025-01-01T02:35:00.000"}
{"ride_id":157,"driver_id":1038,"distance_km":12.4411321596,"fare_usd":10.4435740855,"ride_type":"premium","city":"Berlin","timestamp":"2025-01-01T02:36:00.000"}
{"ride_id":158,"driver_id":1048,"distance_km":4.0959259121,"fare_usd":5.1637573438,"ride_type":"standard","city":"Toronto","timestamp":"2025-01-01T02:37:00.000"}
{"ride_id":159,"driver_id":1031,"distance_km":10.7341418791,"fare_usd":72.7389571745,"ride_type":"standard","city":"Lima","timestamp":"2025-01-01T02:38:00.000"}
{"ride_id":160,"driver_id":1003,"distance_km":5.920717213,"fare_usd":5.3677672991,"ride_type":"pool","city":"Nairobi","timestamp":"2025-01-01T02:39:00.000"}
{"ride_id":161,"driver_id":1029,"distance_km":19.7586024884,"fare_usd":12.216562221,"ride_type":"standard","city":"Lima","timestamp":"2025-01-01T02:40:00.000"}
{"ride_id":162,"driver_id":1036,"distance_km":12.2597831357,"fare_usd":27.0217589767,"ride_type":"premium","city":"Toronto","timestamp":"2025-01-01T02:41:00.000"}
{"ride_id":163,"driver_id":1022,"distance_km":7.6524476254,"fare_usd":61.5201176272,"ride_type":"standard","city":"Berlin","timestamp":"2025-01-01T02:42:00.000"}
{"ride_id":164,"driver_id":1038,"distance_km":8.712199824,"fare_usd":72.3469150035,"ride_type":"pool","city":"Lima","timestamp":"2025-01-01T02:43:00.000"}
{"ride_id":165,"driver_id":1044,"distance_km":11.450007761,"fare_usd":60.3009491154,"ride_type":"premium","city":"Lima","timestamp":"2025-01-01T02:44:00.000"}
{"ride_id":166,"driver_id":1014,"distance_km":8.5385460228,"fare_usd":53.3392162712,"ride_type":"pool","city":"Berlin","timestamp":"2025-01-01T02:45:00.000"}
{"ride_id":167,"driver_id":1042,"distance_km":14.143984558,"fare_usd":41.4910467189,"ride_type":"premium","city":"Nairobi","timestamp":"2025-01-01T02:46:00.000"}
{"ride_id":168,"driver_id":1028,"distance_km":1.9371625822,"fare_usd":11.0693648304,"ride_type":"standard","city":"Berlin","timestamp":"2025-01-01T02:47:00.000"}
{"ride_id":169,"driver_id":1035,"distance_km":9.1131417079,"fare_usd":72.0719555103,"ride_type":"pool","city":"Lima","timestamp":"2025-01-01T02:48:00.000"}
{"ride_id":170,"driver_id":1012,"distance_km":12.9249949053,"fare_usd":58.0874689762,"ride_type":"pool","city":"Nairobi","timestamp":"2025-01-01T02:49:00.000"}
{"ride_id":171,"driver_id":1031,"distance_km":18.4806745787,"fare_usd":49.7264569734,"ride_type":"premium","city":"Nairobi","timestamp":"2025-01-01T02:50:00.000"}
{"ride_id":172,"driver_id":1006,"distance_km":8.8577716329,"fare_usd":58.1325091877,"ride_type":"pool","city":"Berlin","timestamp":"2025-01-01T02:51:00.000"}
{"ride_id":173,"driver_id":1050,"distance_km":4.8623686315,"fare_usd":55.6872330491,"ride_type":"premium","city":"Lima","timestamp":"2025-01-01T02:52:00.000"}
{"ride_id":174,"driver_id":1021,"distance_km":3.2098110084,"fare_usd":49.6062105853,"ride_type":"premium","city":"Toronto","timestamp":"2025-01-01T02:53:00.000"}
{"ride_id":175,"driver_id":1027,"distance_km":28.2754229869,"fare_usd":73.6403760126,"ride_type":"premium","city":"Lima","timestamp":"2025-01-01T02:54:00.000"}
{"ride_id":176,"driver_id":1001,"distance_km":13.0825326744,"fare_usd":68.2354668845,"ride_type":"premium","city":"Seoul","timestamp":"2025-01-01T02:55:00.000"}
{"ride_id":177,"driver_id":1041,"distance_km":17.8537160142,"fare_usd":50.2665443382,"ride_type":"standard","city":"Toronto","timestamp":"2025-01-01T02:56:00.000"}
{"ride_id":178,"driver_id":1044,"distance_km":27.6561200032,"fare_usd":53.522264802,"ride_type":"premium","city":"Nairobi","timestamp":"2025-01-01T02:57:00.000"}
{"ride_id":179,"driver_id":1005,"distance_km":3.399704181,"fare_usd":8.6117064661,"ride_type":"pool","city":"Toronto","timestamp":"2025-01-01T02:58:00.000"}
{"ride_id":180,"driver_id":1027,"distance_km":26.4231830918,"fare_usd":51.8942225185,"ride_type":"standard","city":"Nairobi","timestamp":"2025-01-01T02:59:00.000"}
{"ride_id":181,"driver_id":1027,"distance_km":16.9960483038,"fare_usd":8.0915806397,"ride_type":"pool","city":"Nairobi","timestamp":"2025-01-01T03:00:00.000"}
{"ride_id":182,"driver_id":1043,"distance_km":5.780193573,"fare_usd":46.1784629879,"ride_type":"standard","city":"Toronto","timestamp":"2025-01-01T03:01:00.000"}
{"ride_id":183,"driver_id":1043,"distance_km":12.926398381,"fare_usd":74.9547449696,"ride_type":"premium","city":"Nairobi","timestamp":"2025-01-01T03:02:00.000"}
{"ride_id":184,"driver_id":1019,"distance_km":23.5504662283,"fare_usd":43.9064607006,"ride_type":"standard","city":"Nairobi","timestamp":"2025-01-01T03:03:00.000"}
{"ride_id":185,"driver_id":1029,"distance_km":14.9307323741,"fare_usd":38.1247082657,"ride_type":"standard","city":"Seoul","timestamp":"2025-01-01T03:04:00.000"}
{"ride_id":186,"driver_id":1010,"distance_km":29.5732954693,"fare_usd":26.8998399554,"ride_type":"pool","city":"Lima","timestamp":"2025-01-01T03:05:00.000"}
{"ride_id":187,"driver_id":1027,"distance_km":11.9254301282,"fare_usd":13.4365805151,"ride_type":"pool","city":"Lima","timestamp":"2025-01-01T03:06:00.000"}
{"ride_id":188,"driver_id":1024,"distance_km":22.7377706993,"fare_usd":56.1716570021,"ride_type":"premium","city":"Seoul","timestamp":"2025-01-01T03:07:00.000"}
{"ride_id":189,"driver_id":1038,"distance_km":12.3966940204,"fare_usd":18.481931945,"ride_type":"standard","city":"Toronto","timestamp":"2025-01-01T03:08:00.000"}
{"ride_id":190,"driver_id":1032,"distance_km":25.0457624005,"fare_usd":13.0697414873,"ride_type":"standard","city":"Berlin","timestamp":"2025-01-01T03:09:00.000"}
{"ride_id":191,"driver_id":1000,"distance_km":17.5033626058,"fare_usd":34.5233861811,"ride_type":"standard","city":"Berlin","timestamp":"2025-01-01T03:10:00.000"}
{"ride_id":192,"driver_id":1026,"distance_km":2.8418430581,"fare_usd":60.6739286571,"ride_type":"premium","city":"Berlin","timestamp":"2025-01-01T03:11:00.000"}
{"ride_id":193,"driver_id":1012,"distance_km":2.0678341614,"fare_usd":57.1545183684,"ride_type":"premium","city":"Seoul","timestamp":"2025-01-01T03:12:00.000"}
{"ride_id":194,"driver_id":1040,"distance_km":4.8817114452,"fare_usd":8.8417830253,"ride_type":"premium","city":"Seoul","timestamp":"2025-01-01T03:13:00.000"}
{"ride_id":195,"driver_id":1002,"distance_km":1.39648698,"fare_usd":36.8600579525,"ride_type":"premium","city":"Nairobi","timestamp":"2025-01-01T03:14:00.000"}
{"ride_id":196,"driver_id":1038,"distance_km":3.1854127502,"fare_usd":41.570420325,"ride_type":"premium","city":"Berlin","timestamp":"2025-01-01T03:15:00.000"}
{"ride_id":197,"driver_id":1005,"distance_km":21.0597175179,"fare_usd":50.1182655438,"ride_type":"pool","city":"Toronto","timestamp":"2025-01-01T03:16:00.000"}
{"ride_id":198,"driver_id":1007,"distance_km":16.4960419759,"fare_usd":50.511714531,"ride_type":"standard","city":"Toronto","timestamp":"2025-01-01T03:17:00.000"}
{"ride_id":199,"driver_id":1026,"distance_km":22.7474117346,"fare_usd":30.528807462,"ride_type":"standard","city":"Berlin","timestamp":"2025-01-01T03:18:00.000"}
{"ride_id":200,"driver_id":1008,"distance_km":27.4818068155,"fare_usd":44.2474035802,"ride_type":"standard","city":"Berlin","timestamp":"2025-01-01T03:19:00.000"}
{"ride_id":201,"driver_id":1036,"distance_km":17.9693364374,"fare_usd":38.6743318691,"ride_type":"standard","city":"Berlin","timestamp":"2025-01-01T03:20:00.000"}
{"ride_id":202,"driver_id":1032,"distance_km":22.0575044781,"fare_usd":66.9498849566,"ride_type":"standard","city":"Seoul","timestamp":"2025-01-01T03:21:00.000"}
{"ride_id":203,"driver_id":1050,"distance_km":22.9553548592,"fare_usd":42.1185592844,"ride_type":"standard","city":"Seoul","timestamp":"2025-01-01T03:22:00.000"}
{"ride_id":204,"driver_id":1041,"distance_km":11.957665929,"fare_usd":35.8722513224,"ride_type":"standard","city":"Seoul","timestamp":"2025-01-01T03:23:00.000"}
{"ride_id":205,"driver_id":1043,"distance_km":7.9914601376,"fare_usd":33.3139814777,"ride_type":"standard","city":"Lima","timestamp":"2025-01-01T03:24:00.000"}
{"ride_id":206,"driver_id":1023,"distance_km":6.9463145267,"fare_usd":45.0699431603,"ride_type":"pool","city":"Toronto","timestamp":"2025-01-01T03:25:00.000"}
{"ride_id":207,"driver_id":1014,"distance_km":8.2918307458,"fare_usd":61.2783885581,"ride_type":"standard","city":"Toronto","timestamp":"2025-01-01T03:26:00.000"}
{"ride_id":208,"driver_id":1031,"distance_km":8.9672221138,"fare_usd":42.6881043267,"ride_type":"pool","city":"Nairobi","timestamp":"2025-01-01T03:27:00.000"}
{"ride_id":209,"driver_id":1031,"distance_km":7.0096018212,"fare_usd":51.3158622556,"ride_type":"premium","city":"Seoul","timestamp":"2025-01-01T03:28:00.000"}
{"ride_id":210,"driver_id":1023,"distance_km":26.4683993569,"fare_usd":56.6499036835,"ride_type":"standard","city":"Lima","timestamp":"2025-01-01T03:29:00.000"}
{"ride_id":211,"driver_id":1040,"distance_km":22.952974833,"fare_usd":41.4117676915,"ride_type":"premium","city":"Lima","timestamp":"2025-01-01T03:30:00.000"}
{"ride_id":212,"driver_id":1048,"distance_km":2.3599975659,"fare_usd":34.8771939658,"ride_type":"premium","city":"Toronto","timestamp":"2025-01-01T03:31:00.000"}
{"ride_id":213,"driver_id":1048,"distance_km":8.7915019787,"fare_usd":66.3665764504,"ride_type":"premium","city":"Seoul","timestamp":"2025-01-01T03:32:00.000"}
{"ride_id":214,"driver_id":1011,"distance_km":1.6433575189,"fare_usd":34.225425882,"ride_type":"pool","city":"Nairobi","timestamp":"2025-01-01T03:33:00.000"}
{"ride_id":215,"driver_id":1038,"distance_km":15.4467904127,"fare_usd":37.3359995403,"ride_type":"premium","city":"Seoul","timestamp":"2025-01-01T03:34:00.000"}
{"ride_id":216,"driver_id":1001,"distance_km":14.8101102069,"fare_usd":74.3238919339,"ride_type":"premium","city":"Berlin","timestamp":"2025-01-01T03:35:00.000"}
{"ride_id":217,"driver_id":1002,"distance_km":25.1097732118,"fare_usd":5.0166266503,"ride_type":"premium","city":"Seoul","timestamp":"2025-01-01T03:36:00.000"}
{"ride_id":218,"driver_id":1048,"distance_km":9.9255399534,"fare_usd":17.9831036704,"ride_type":"standard","city":"Berlin","timestamp":"2025-01-01T03:37:00.000"}
{"ride_id":219,"driver_id":1036,"distance_km":24.6751863212,"fare_usd":31.8774722944,"ride_type":"standard","city":"Berlin","timestamp":"2025-01-01T03:38:00.000"}
{"ride_id":220,"driver_id":1048,"distance_km":29.0712391978,"fare_usd":70.2812936598,"ride_type":"pool","city":"Nairobi","timestamp":"2025-01-01T03:39:00.000"}
{"ride_id":221,"driver_id":1016,"distance_km":3.5638384776,"fare_usd":9.9020794023,"ride_type":"pool","city":"Toronto","timestamp":"2025-01-01T03:40:00.000"}
{"ride_id":222,"driver_id":1048,"distance_km":23.9627173446,"fare_usd":5.663980354,"ride_type":"standard","city":"Seoul","timestamp":"2025-01-01T03:41:00.000"}
{"ride_id":223,"driver_id":1001,"distance_km":18.108721017,"fare_usd":8.6878685184,"ride_type":"pool","city":"Berlin","timestamp":"2025-01-01T03:42:00.000"}
{"ride_id":224,"driver_id":1001,"distance_km":14.9213330435,"fare_usd":11.198038743,"ride_type":"standard","city":"Seoul","timestamp":"2025-01-01T03:43:00.000"}
{"ride_id":225,"driver_id":1027,"distance_km":13.1955375813,"fare_usd":7.6317741244,"ride_type":"premium","city":"Toronto","timestamp":"2025-01-01T03:44:00.000"}
{"ride_id":226,"driver_id":1022,"distance_km":23.7553796544,"fare_usd":38.58469288,"ride_type":"premium","city":"Toronto","timestamp":"2025-01-01T03:45:00.000"}
{"ride_id":227,"driver_id":1036,"distance_km":19.5414793523,"fare_usd":45.6530045059,"ride_type":"pool","city":"Lima","timestamp":"2025-01-01T03:46:00.000"}
{"ride_id":228,"driver_id":1031,"distance_km":24.3462953581,"fare_usd":24.0180879748,"ride_type":"standard","city":"Toronto","timestamp":"2025-01-01T03:47:00.000"}
{"ride_id":229,"driver_id":1032,"distance_km":27.1913807016,"fare_usd":32.8801168783,"ride_type":"standard","city":"Nairobi","timestamp":"2025-01-01T03:48:00.000"}
{"ride_id":230,"driver_id":1000,"distance_km":18.9006476508,"fare_usd":11.4189534578,"ride_type":"pool","city":"Berlin","timestamp":"2025-01-01T03:49:00.000"}
{"ride_id":231,"driver_id":1018,"distance_km":29.4334190277,"fare_usd":28.545932468,"ride_type":"standard","city":"Lima","timestamp":"2025-01-01T03:50:00.000"}
{"ride_id":232,"driver_id":1001,"distance_km":18.6345476367,"fare_usd":41.5763434144,"ride_type":"premium","city":"Nairobi","timestamp":"2025-01-01T03:51:00.000"}
{"ride_id":233,"driver_id":1043,"distance_km":19.462685327,"fare_usd":56.2590265029,"ride_type":"pool","city":"Seoul","timestamp":"2025-01-01T03:52:00.000"}
{"ride_id":234,"driver_id":1025,"distance_km":17.0896526477,"fare_usd":5.234245343,"ride_type":"pool","city":"Berlin","timestamp":"2025-01-01T03:53:00.000"}
{"ride_id":235,"driver_id":1031,"distance_km":3.6390606405,"fare_usd":37.7117536576,"ride_type":"standard","city":"Toronto","timestamp":"2025-01-01T03:54:00.000"}
{"ride_id":236,"driver_id":1005,"distance_km":22.0655139469,"fare_usd":25.7902013518,"ride_type":"pool","city":"Berlin","timestamp":"2025-01-01T03:55:00.000"}
{"ride_id":237,"driver_id":1031,"distance_km":16.8759429001,"fare_usd":64.6975275184,"ride_type":"standard","city":"Seoul","timestamp":"2025-01-01T03:56:00.000"}
{"ride_id":238,"driver_id":1003,"distance_km":14.0764029751,"fare_usd":55.0887320664,"ride_type":"standard","city":"Lima","timestamp":"2025-01-01T03:57:00.000"}
{"ride_id":239,"driver_id":1010,"distance_km":27.4036670737,"fare_usd":46.237597413,"ride_type":"standard","city":"Lima","timestamp":"2025-01-01T03:58:00.000"}
{"ride_id":240,"driver_id":1016,"distance_km":9.6408240947,"fare_usd":24.4085951988,"ride_type":"standard","city":"Lima","timestamp":"2025-01-01T03:59:00.000"}
{"ride_id":241,"driver_id":1037,"distance_km":16.1844660044,"fare_usd":68.723737144,"ride_type":"standard","city":"Toronto","timestamp":"2025-01-01T04:00:00.000"}
{"ride_id":242,"driver_id":1023,"distance_km":21.2316142733,"fare_usd":8.1570474054,"ride_type":"pool","city":"Nairobi","timestamp":"2025-01-01T04:01:00.000"}
{"ride_id":243,"driver_id":1004,"distance_km":24.0976814945,"fare_usd":12.6627319075,"ride_type":"premium","city":"Nairobi","timestamp":"2025-01-01T04:02:00.000"}
{"ride_id":244,"driver_id":1033,"distance_km":14.3210574304,"fare_usd":32.4141098378,"ride_type":"premium","city":"Berlin","timestamp":"2025-01-01T04:03:00.000"}
{"ride_id":245,"driver_id":1005,"distance_km":25.4206510355,"fare_usd":13.7106290108,"ride_type":"pool","city":"Toronto","timestamp":"2025-01-01T04:04:00.000"}
{"ride_id":246,"driver_id":1021,"distance_km":23.2986144981,"fare_usd":71.9490988292,"ride_type":"pool","city":"Lima","timestamp":"2025-01-01T04:05:00.000"}
{"ride_id":247,"driver_id":1010,"distance_km":2.9208433577,"fare_usd":60.85925255,"ride_type":"premium","city":"Lima","timestamp":"2025-01-01T04:06:00.000"}
{"ride_id":248,"driver_id":1047,"distance_km":2.3299767257,"fare_usd":23.1287856121,"ride_type":"premium","city":"Seoul","timestamp":"2025-01-01T04:07:00.000"}
{"ride_id":249,"driver_id":1015,"distance_km":19.0033648482,"fare_usd":46.1987960281,"ride_type":"premium","city":"Seoul","timestamp":"2025-01-01T04:08:00.000"}
{"ride_id":250,"driver_id":1032,"distance_km":11.0749888385,"fare_usd":73.7631360556,"ride_type":"premium","city":"Lima","timestamp":"2025-01-01T04:09:00.000"}
{"ride_id":251,"driver_id":1008,"distance_km":7.0647929413,"fare_usd":66.8939284692,"ride_type":"premium","city":"Lima","timestamp":"2025-01-01T04:10:00.000"}
{"ride_id":252,"driver_id":1005,"distance_km":17.8098480997,"fare_usd":47.055891251,"ride_type":"standard","city":"Toronto","timestamp":"2025-01-01T04:11:00.000"}
{"ride_id":253,"driver_id":1015,"distance_km":10.9053331032,"fare_usd":68.2606777023,"ride_type":"pool","city":"Nairobi","timestamp":"2025-01-01T04:12:00.000"}
{"ride_id":254,"driver_id":1028,"distance_km":16.5806390847,"fare_usd":74.2429436869,"ride_type":"standard","city":"Seoul","timestamp":"2025-01-01T04:13:00.000"}
{"ride_id":255,"driver_id":1002,"distance_km":14.3434556105,"fare_usd":57.0346976026,"ride_type":"premium","city":"Nairobi","timestamp":"2025-01-01T04:14:00.000"}
{"ride_id":256,"driver_id":1019,"distance_km":17.9582170725,"fare_usd":9.5490486638,"ride_type":"premium","city":"Toronto","timestamp":"2025-01-01T04:15:00.000"}
{"ride_id":257,"driver_id":1035,"distance_km":12.6087141784,"fare_usd":33.1106165498,"ride_type":"premium","city":"Lima","timestamp":"2025-01-01T04:16:00.000"}
{"ride_id":258,"driver_id":1018,"distance_km":21.2323596372,"fare_usd":63.6478014698,"ride_type":"standard","city":"Nairobi","timestamp":"2025-01-01T04:17:00.000"}
{"ride_id":259,"driver_id":1025,"distance_km":6.2219508981,"fare_usd":21.1398437064,"ride_type":"standard","city":"Lima","timestamp":"2025-01-01T04:18:00.000"}
{"ride_id":260,"driver_id":1002,"distance_km":21.1985425206,"fare_usd":63.1449762425,"ride_type":"premium","city":"Lima","timestamp":"2025-01-01T04:19:00.000"}
{"ride_id":261,"driver_id":1018,"distance_km":12.9381752164,"fare_usd":13.4237133424,"ride_type":"standard","city":"Berlin","timestamp":"2025-01-01T04:20:00.000"}
{"ride_id":262,"driver_id":1019,"distance_km":26.3552105408,"fare_usd":8.2861750003,"ride_type":"standard","city":"Nairobi","timestamp":"2025-01-01T04:21:00.000"}
{"ride_id":263,"driver_id":1031,"distance_km":15.9418455911,"fare_usd":31.8863428044,"ride_type":"premium","city":"Nairobi","timestamp":"2025-01-01T04:22:00.000"}
{"ride_id":264,"driver_id":1006,"distance_km":29.2202001288,"fare_usd":7.5712356199,"ride_type":"standard","city":"Lima","timestamp":"2025-01-01T04:23:00.000"}
{"ride_id":265,"driver_id":1040,"distance_km":18.4561264707,"fare_usd":72.0089184088,"ride_type":"pool","city":"Toronto","timestamp":"2025-01-01T04:24:00.000"}
{"ride_id":266,"driver_id":1032,"distance_km":7.4916229113,"fare_usd":62.8343987056,"ride_type":"pool","city":"Berlin","timestamp":"2025-01-01T04:25:00.000"}
{"ride_id":267,"driver_id":1039,"distance_km":24.8319284685,"fare_usd":61.0538780991,"ride_type":"pool","city":"Lima","timestamp":"2025-01-01T04:26:00.000"}
{"ride_id":268,"driver_id":1038,"distance_km":11.0073962068,"fare_usd":49.0844546097,"ride_type":"pool","city":"Seoul","timestamp":"2025-01-01T04:27:00.000"}
{"ride_id":269,"driver_id":1017,"distance_km":11.08095722,"fare_usd":20.1426816126,"ride_type":"premium","city":"Seoul","timestamp":"2025-01-01T04:28:00.000"}
{"ride_id":270,"driver_id":1039,"distance_km":1.9223357631,"fare_usd":41.2782256673,"ride_type":"premium","city":"Berlin","timestamp":"2025-01-01T04:29:00.000"}
{"ride_id":271,"driver_id":1000,"distance_km":16.912743967,"fare_usd":46.8091850701,"ride_type":"premium","city":"Toronto","timestamp":"2025-01-01T04:30:00.000"}
{"ride_id":272,"driver_id":1010,"distance_km":16.4982816082,"fare_usd":41.7522050602,"ride_type":"pool","city":"Lima","timestamp":"2025-01-01T04:31:00.000"}
{"ride_id":273,"driver_id":1027,"distance_km":11.3237530439,"fare_usd":23.2163357566,"ride_type":"pool","city":"Nairobi","timestamp":"2025-01-01T04:32:00.000"}
{"ride_id":274,"driver_id":1024,"distance_km":26.932300624,"fare_usd":41.067354702,"ride_type":"standard","city":"Berlin","timestamp":"2025-01-01T04:33:00.000"}
{"ride_id":275,"driver_id":1049,"distance_km":4.7337035507,"fare_usd":39.3830438608,"ride_type":"standard","city":"Toronto","timestamp":"2025-01-01T04:34:00.000"}
{"ride_id":276,"driver_id":1022,"distance_km":10.572885886,"fare_usd":74.7435043065,"ride_type":"pool","city":"Nairobi","timestamp":"2025-01-01T04:35:00.000"}
{"ride_id":277,"driver_id":1030,"distance_km":10.3259001757,"fare_usd":67.8205303632,"ride_type":"pool","city":"Seoul","timestamp":"2025-01-01T04:36:00.000"}
{"ride_id":278,"driver_id":1029,"distance_km":3.6764270006,"fare_usd":37.4366523751,"ride_type":"pool","city":"Seoul","timestamp":"2025-01-01T04:37:00.000"}
{"ride_id":279,"driver_id":1041,"distance_km":14.9532164276,"fare_usd":48.6056168055,"ride_type":"pool","city":"Nairobi","timestamp":"2025-01-01T04:38:00.000"}
{"ride_id":280,"driver_id":1034,"distance_km":20.9457567958,"fare_usd":57.3510122865,"ride_type":"standard","city":"Berlin","timestamp":"2025-01-01T04:39:00.000"}
{"ride_id":281,"driver_id":1006,"distance_km":15.8380533929,"fare_usd":7.4405612164,"ride_type":"pool","city":"Seoul","timestamp":"2025-01-01T04:40:00.000"}
{"ride_id":282,"driver_id":1015,"distance_km":5.5523527988,"fare_usd":67.6445008859,"ride_type":"standard","city":"Lima","timestamp":"2025-01-01T04:41:00.000"}
{"ride_id":283,"driver_id":1025,"distance_km":11.941292992,"fare_usd":65.2088771493,"ride_type":"pool","city":"Nairobi","timestamp":"2025-01-01T04:42:00.000"}
{"ride_id":284,"driver_id":1047,"distance_km":1.0752557071,"fare_usd":37.0202468442,"ride_type":"pool","city":"Nairobi","timestamp":"2025-01-01T04:43:00.000"}
{"ride_id":285,"driver_id":1048,"distance_km":26.180732104,"fare_usd":32.3818836256,"ride_type":"pool","city":"Seoul","timestamp":"2025-01-01T04:44:00.000"}
{"ride_id":286,"driver_id":1001,"distance_km":3.4509932227,"fare_usd":24.1071562399,"ride_type":"standard","city":"Berlin","timestamp":"2025-01-01T04:45:00.000"}
{"ride_id":287,"driver_id":1000,"distance_km":18.3210643854,"fare_usd":38.3673779831,"ride_type":"standard","city":"Lima","timestamp":"2025-01-01T04:46:00.000"}
{"ride_id":288,"driver_id":1047,"distance_km":29.6014528801,"fare_usd":8.1063664473,"ride_type":"premium","city":"Berlin","timestamp":"2025-01-01T04:47:00.000"}
{"ride_id":289,"driver_id":1011,"distance_km":16.5611287336,"fare_usd":64.6535473343,"ride_type":"pool","city":"Toronto","timestamp":"2025-01-01T04:48:00.000"}
{"ride_id":290,"driver_id":1004,"distance_km":27.7972110141,"fare_usd":7.4795657893,"ride_type":"premium","city":"Toronto","timestamp":"2025-01-01T04:49:00.000"}
{"ride_id":291,"driver_id":1036,"distance_km":7.8473794604,"fare_usd":28.0335955759,"ride_type":"premium","city":"Seoul","timestamp":"2025-01-01T04:50:00.000"}
{"ride_id":292,"driver_id":1031,"distance_km":23.0387068592,"fare_usd":70.2112641823,"ride_type":"standard","city":"Seoul","timestamp":"2025-01-01T04:51:00.000"}
{"ride_id":293,"driver_id":1008,"distance_km":16.4067068652,"fare_usd":56.4648858166,"ride_type":"standard","city":"Seoul","timestamp":"2025-01-01T04:52:00.000"}
{"ride_id":294,"driver_id":1040,"distance_km":21.8949657804,"fare_usd":24.6973672404,"ride_type":"premium","city":"Toronto","timestamp":"2025-01-01T04:53:00.000"}
{"ride_id":295,"driver_id":1034,"distance_km":2.8078995128,"fare_usd":22.6854365773,"ride_type":"pool","city":"Berlin","timestamp":"2025-01-01T04:54:00.000"}
{"ride_id":296,"driver_id":1018,"distance_km":5.2844336653,"fare_usd":5.3557497873,"ride_type":"standard","city":"Berlin","timestamp":"2025-01-01T04:55:00.000"}
{"ride_id":297,"driver_id":1047,"distance_km":4.860390929,"fare_usd":53.7000004995,"ride_type":"pool","city":"Seoul","timestamp":"2025-01-01T04:56:00.000"}
{"ride_id":298,"driver_id":1015,"distance_km":20.9277996567,"fare_usd":8.4148507171,"ride_type":"pool","city":"Lima","timestamp":"2025-01-01T04:57:00.000"}
{"ride_id":299,"driver_id":1002,"distance_km":25.4887795064,"fare_usd":42.2821763581,"ride_type":"premium","city":"Berlin","timestamp":"2025-01-01T04:58:00.000"}
{"ride_id":300,"driver_id":1019,"distance_km":22.7388707282,"fare_usd":72.3485380814,"ride_type":"premium","city":"Toronto","timestamp":"2025-01-01T04:59:00.000"}
{"ride_id":301,"driver_id":1023,"distance_km":1.8836924293,"fare_usd":12.6628202038,"ride_type":"premium","city":"Nairobi","timestamp":"2025-01-01T05:00:00.000"}
{"ride_id":302,"driver_id":1032,"distance_km":26.1492344512,"fare_usd":67.6135951678,"ride_type":"premium","city":"Nairobi","timestamp":"2025-01-01T05:01:00.000"}
{"ride_id":303,"driver_id":1023,"distance_km":11.270253453,"fare_usd":74.4032734602,"ride_type":"standard","city":"Nairobi","timestamp":"2025-01-01T05:02:00.000"}
{"ride_id":304,"driver_id":1010,"distance_km":12.5177511426,"fare_usd":9.3061918367,"ride_type":"standard","city":"Lima","timestamp":"2025-01-01T05:03:00.000"}
{"ride_id":305,"driver_id":1048,"distance_km":4.0412058294,"fare_usd":66.8034388396,"ride_type":"premium","city":"Seoul","timestamp":"2025-01-01T05:04:00.000"}
{"ride_id":306,"driver_id":1007,"distance_km":22.3847509767,"fare_usd":41.1255314311,"ride_type":"standard","city":"Toronto","timestamp":"2025-01-01T05:05:00.000"}
{"ride_id":307,"driver_id":1035,"distance_km":6.2862324758,"fare_usd":68.4559603611,"ride_type":"premium","city":"Lima","timestamp":"2025-01-01T05:06:00.000"}
{"ride_id":308,"driver_id":1037,"distance_km":17.3549876685,"fare_usd":44.9923259344,"ride_type":"pool","city":"Toronto","timestamp":"2025-01-01T05:07:00.000"}
{"ride_id":309,"driver_id":1039,"distance_km":25.3805895905,"fare_usd":51.3478407075,"ride_type":"pool","city":"Toronto","timestamp":"2025-01-01T05:08:00.000"}
{"ride_id":310,"driver_id":1019,"distance_km":3.5869255326,"fare_usd":43.0645235598,"ride_type":"pool","city":"Seoul","timestamp":"2025-01-01T05:09:00.000"}
{"ride_id":311,"driver_id":1034,"distance_km":16.5247313565,"fare_usd":65.5145016215,"ride_type":"premium","city":"Nairobi","timestamp":"2025-01-01T05:10:00.000"}
{"ride_id":312,"driver_id":1047,"distance_km":7.7632759349,"fare_usd":56.3736943268,"ride_type":"pool","city":"Seoul","timestamp":"2025-01-01T05:11:00.000"}
{"ride_id":313,"driver_id":1024,"distance_km":10.9448790641,"fare_usd":41.4882218526,"ride_type":"standard","city":"Lima","timestamp":"2025-01-01T05:12:00.000"}
{"ride_id":314,"driver_id":1034,"distance_km":14.7451283015,"fare_usd":65.7712562836,"ride_type":"pool","city":"Lima","timestamp":"2025-01-01T05:13:00.000"}
{"ride_id":315,"driver_id":1024,"distance_km":11.2980247951,"fare_usd":22.1699872579,"ride_type":"pool","city":"Lima","timestamp":"2025-01-01T05:14:00.000"}
{"ride_id":316,"driver_id":1028,"distance_km":19.8158623685,"fare_usd":16.0138461792,"ride_type":"pool","city":"Seoul","timestamp":"2025-01-01T05:15:00.000"}
{"ride_id":317,"driver_id":1017,"distance_km":14.9078809509,"fare_usd":16.2280073731,"ride_type":"standard","city":"Toronto","timestamp":"2025-01-01T05:16:00.000"}
{"ride_id":318,"driver_id":1045,"distance_km":17.9417850567,"fare_usd":28.3806215122,"ride_type":"premium","city":"Toronto","timestamp":"2025-01-01T05:17:00.000"}
{"ride_id":319,"driver_id":1017,"distance_km":22.3678517865,"fare_usd":21.7083021911,"ride_type":"standard","city":"Berlin","timestamp":"2025-01-01T05:18:00.000"}
{"ride_id":320,"driver_id":1001,"distance_km":17.1745257126,"fare_usd":70.1063245357,"ride_type":"premium","city":"Lima","timestamp":"2025-01-01T05:19:00.000"}
{"ride_id":321,"driver_id":1034,"distance_km":18.0095276052,"fare_usd":12.408386568,"ride_type":"premium","city":"Toronto","timestamp":"2025-01-01T05:20:00.000"}
{"ride_id":322,"driver_id":1015,"distance_km":17.3692977332,"fare_usd":53.9293516628,"ride_type":"pool","city":"Berlin","timestamp":"2025-01-01T05:21:00.000"}
{"ride_id":323,"driver_id":1040,"distance_km":11.9844061526,"fare_usd":18.245507785,"ride_type":"premium","city":"Toronto","timestamp":"2025-01-01T05:22:00.000"}
{"ride_id":324,"driver_id":1035,"distance_km":10.7859581823,"fare_usd":66.7145992939,"ride_type":"standard","city":"Lima","timestamp":"2025-01-01T05:23:00.000"}
{"ride_id":325,"driver_id":1032,"distance_km":27.0897745172,"fare_usd":72.2920701729,"ride_type":"standard","city":"Nairobi","timestamp":"2025-01-01T05:24:00.000"}
{"ride_id":326,"driver_id":1003,"distance_km":18.6191014465,"fare_usd":37.5829006139,"ride_type":"premium","city":"Lima","timestamp":"2025-01-01T05:25:00.000"}
{"ride_id":327,"driver_id":1032,"distance_km":8.0862415085,"fare_usd":66.535003616,"ride_type":"pool","city":"Seoul","timestamp":"2025-01-01T05:26:00.000"}
{"ride_id":328,"driver_id":1013,"distance_km":15.4491832376,"fare_usd":5.3601619528,"ride_type":"pool","city":"Toronto","timestamp":"2025-01-01T05:27:00.000"}
{"ride_id":329,"driver_id":1020,"distance_km":10.5801059571,"fare_usd":62.3962842186,"ride_type":"standard","city":"Toronto","timestamp":"2025-01-01T05:28:00.000"}
{"ride_id":330,"driver_id":1047,"distance_km":28.077062889,"fare_usd":21.0037613067,"ride_type":"pool","city":"Seoul","timestamp":"2025-01-01T05:29:00.000"}
{"ride_id":331,"driver_id":1019,"distance_km":1.2184965309,"fare_usd":68.6090916489,"ride_type":"premium","city":"Seoul","timestamp":"2025-01-01T05:30:00.000"}
{"ride_id":332,"driver_id":1007,"distance_km":7.5346511337,"fare_usd":5.0784078036,"ride_type":"premium","city":"Nairobi","timestamp":"2025-01-01T05:31:00.000"}
{"ride_id":333,"driver_id":1006,"distance_km":11.5953477705,"fare_usd":43.9327214528,"ride_type":"standard","city":"Toronto","timestamp":"2025-01-01T05:32:00.000"}
{"ride_id":334,"driver_id":1002,"distance_km":15.1464842235,"fare_usd":57.9645062649,"ride_type":"premium","city":"Toronto","timestamp":"2025-01-01T05:33:00.000"}
{"ride_id":335,"driver_id":1016,"distance_km":25.6737080172,"fare_usd":23.1081831489,"ride_type":"standard","city":"Nairobi","timestamp":"2025-01-01T05:34:00.000"}
{"ride_id":336,"driver_id":1032,"distance_km":3.5487411117,"fare_usd":18.5193005211,"ride_type":"premium","city":"Berlin","timestamp":"2025-01-01T05:35:00.000"}
{"ride_id":337,"driver_id":1047,"distance_km":24.3700817155,"fare_usd":10.8868757128,"ride_type":"standard","city":"Nairobi","timestamp":"2025-01-01T05:36:00.000"}
{"ride_id":338,"driver_id":1011,"distance_km":2.6139511914,"fare_usd":27.8503503552,"ride_type":"pool","city":"Lima","timestamp":"2025-01-01T05:37:00.000"}
{"ride_id":339,"driver_id":1050,"distance_km":25.4271070236,"fare_usd":44.1891018616,"ride_type":"premium","city":"Toronto","timestamp":"2025-01-01T05:38:00.000"}
{"ride_id":340,"driver_id":1021,"distance_km":2.4974288584,"fare_usd":13.1090699746,"ride_type":"premium","city":"Seoul","timestamp":"2025-01-01T05:39:00.000"}
{"ride_id":341,"driver_id":1021,"distance_km":1.5290319614,"fare_usd":31.3686753391,"ride_type":"standard","city":"Lima","timestamp":"2025-01-01T05:40:00.000"}
{"ride_id":342,"driver_id":1045,"distance_km":21.2118824086,"fare_usd":5.6350683257,"ride_type":"standard","city":"Toronto","timestamp":"2025-01-01T05:41:00.000"}
{"ride_id":343,"driver_id":1029,"distance_km":29.9204105083,"fare_usd":62.307559435,"ride_type":"premium","city":"Nairobi","timestamp":"2025-01-01T05:42:00.000"}
{"ride_id":344,"driver_id":1037,"distance_km":27.0016976262,"fare_usd":13.9914102665,"ride_type":"standard","city":"Lima","timestamp":"2025-01-01T05:43:00.000"}
{"ride_id":345,"driver_id":1037,"distance_km":17.7039541164,"fare_usd":24.8340063786,"ride_type":"premium","city":"Toronto","timestamp":"2025-01-01T05:44:00.000"}
{"ride_id":346,"driver_id":1044,"distance_km":27.6044727795,"fare_usd":6.2899403117,"ride_type":"pool","city":"Berlin","timestamp":"2025-01-01T05:45:00.000"}
{"ride_id":347,"driver_id":1050,"distance_km":1.1537001855,"fare_usd":35.2568548725,"ride_type":"standard","city":"Berlin","timestamp":"2025-01-01T05:46:00.000"}
{"ride_id":348,"driver_id":1007,"distance_km":29.2769477254,"fare_usd":63.8085051919,"ride_type":"premium","city":"Seoul","timestamp":"2025-01-01T05:47:00.000"}
{"ride_id":349,"driver_id":1026,"distance_km":15.2317145985,"fare_usd":32.4505848012,"ride_type":"pool","city":"Toronto","timestamp":"2025-01-01T05:48:00.000"}
{"ride_id":350,"driver_id":1026,"distance_km":21.963986802,"fare_usd":17.5648126397,"ride_type":"pool","city":"Berlin","timestamp":"2025-01-01T05:49:00.000"}
{"ride_id":351,"driver_id":1033,"distance_km":24.8049827214,"fare_usd":57.7589183835,"ride_type":"premium","city":"Nairobi","timestamp":"2025-01-01T05:50:00.000"}
{"ride_id":352,"driver_id":1020,"distance_km":21.8352608543,"fare_usd":60.216488731,"ride_type":"standard","city":"Toronto","timestamp":"2025-01-01T05:51:00.000"}
{"ride_id":353,"driver_id":1029,"distance_km":16.5160652293,"fare_usd":17.1627432715,"ride_type":"premium","city":"Nairobi","timestamp":"2025-01-01T05:52:00.000"}
{"ride_id":354,"driver_id":1032,"distance_km":14.8219650397,"fare_usd":58.9597875979,"ride_type":"pool","city":"Nairobi","timestamp":"2025-01-01T05:53:00.000"}
{"ride_id":355,"driver_id":1027,"distance_km":25.3188942024,"fare_usd":71.3108521779,"ride_type":"premium","city":"Berlin","timestamp":"2025-01-01T05:54:00.000"}
{"ride_id":356,"driver_id":1046,"distance_km":6.9472492443,"fare_usd":16.6464310853,"ride_type":"standard","city":"Toronto","timestamp":"2025-01-01T05:55:00.000"}
{"ride_id":357,"driver_id":1032,"distance_km":29.0718279286,"fare_usd":58.9689004772,"ride_type":"pool","city":"Lima","timestamp":"2025-01-01T05:56:00.000"}
{"ride_id":358,"driver_id":1004,"distance_km":21.6176218863,"fare_usd":54.6000403222,"ride_type":"premium","city":"Berlin","timestamp":"2025-01-01T05:57:00.000"}
{"ride_id":359,"driver_id":1047,"distance_km":6.7857008928,"fare_usd":38.1501721905,"ride_type":"standard","city":"Berlin","timestamp":"2025-01-01T05:58:00.000"}
{"ride_id":360,"driver_id":1018,"distance_km":22.3511683273,"fare_usd":9.0544322391,"ride_type":"pool","city":"Toronto","timestamp":"2025-01-01T05:59:00.000"}
{"ride_id":361,"driver_id":1003,"distance_km":16.3653606723,"fare_usd":10.228609243,"ride_type":"standard","city":"Toronto","timestamp":"2025-01-01T06:00:00.000"}
{"ride_id":362,"driver_id":1034,"distance_km":21.5096727737,"fare_usd":64.6690261439,"ride_type":"pool","city":"Nairobi","timestamp":"2025-01-01T06:01:00.000"}
{"ride_id":363,"driver_id":1048,"distance_km":23.2656055418,"fare_usd":74.3103860925,"ride_type":"premium","city":"Toronto","timestamp":"2025-01-01T06:02:00.000"}
{"ride_id":364,"driver_id":1016,"distance_km":3.5314152081,"fare_usd":52.3236580031,"ride_type":"standard","city":"Nairobi","timestamp":"2025-01-01T06:03:00.000"}
{"ride_id":365,"driver_id":1043,"distance_km":15.6770147344,"fare_usd":36.2170814907,"ride_type":"pool","city":"Berlin","timestamp":"2025-01-01T06:04:00.000"}
{"ride_id":366,"driver_id":1027,"distance_km":28.0284159255,"fare_usd":50.3301550381,"ride_type":"standard","city":"Seoul","timestamp":"2025-01-01T06:05:00.000"}
{"ride_id":367,"driver_id":1029,"distance_km":10.2986235726,"fare_usd":46.607710146,"ride_type":"standard","city":"Lima","timestamp":"2025-01-01T06:06:00.000"}
{"ride_id":368,"driver_id":1028,"distance_km":18.2226098292,"fare_usd":31.8528582284,"ride_type":"premium","city":"Berlin","timestamp":"2025-01-01T06:07:00.000"}
{"ride_id":369,"driver_id":1045,"distance_km":11.7076839638,"fare_usd":9.5938301202,"ride_type":"standard","city":"Toronto","timestamp":"2025-01-01T06:08:00.000"}
{"ride_id":370,"driver_id":1005,"distance_km":14.1737711944,"fare_usd":62.5059063185,"ride_type":"pool","city":"Lima","timestamp":"2025-01-01T06:09:00.000"}
{"ride_id":371,"driver_id":1034,"distance_km":16.9094904202,"fare_usd":31.0283470467,"ride_type":"pool","city":"Seoul","timestamp":"2025-01-01T06:10:00.000"}
{"ride_id":372,"driver_id":1040,"distance_km":16.9187374168,"fare_usd":62.314995035,"ride_type":"pool","city":"Seoul","timestamp":"2025-01-01T06:11:00.000"}
{"ride_id":373,"driver_id":1036,"distance_km":6.8501834076,"fare_usd":22.6756124782,"ride_type":"pool","city":"Nairobi","timestamp":"2025-01-01T06:12:00.000"}
{"ride_id":374,"driver_id":1023,"distance_km":20.8525748885,"fare_usd":5.0720635892,"ride_type":"premium","city":"Lima","timestamp":"2025-01-01T06:13:00.000"}
{"ride_id":375,"driver_id":1028,"distance_km":3.548175226,"fare_usd":16.1256798294,"ride_type":"standard","city":"Nairobi","timestamp":"2025-01-01T06:14:00.000"}
{"ride_id":376,"driver_id":1048,"distance_km":5.0259184298,"fare_usd":37.7977591738,"ride_type":"premium","city":"Berlin","timestamp":"2025-01-01T06:15:00.000"}
{"ride_id":377,"driver_id":1045,"distance_km":1.078616083,"fare_usd":71.101254447,"ride_type":"standard","city":"Lima","timestamp":"2025-01-01T06:16:00.000"}
{"ride_id":378,"driver_id":1030,"distance_km":4.3841858601,"fare_usd":12.1535533786,"ride_type":"standard","city":"Berlin","timestamp":"2025-01-01T06:17:00.000"}
{"ride_id":379,"driver_id":1034,"distance_km":14.7218198305,"fare_usd":64.7946842123,"ride_type":"standard","city":"Nairobi","timestamp":"2025-01-01T06:18:00.000"}
{"ride_id":380,"driver_id":1032,"distance_km":18.5769545506,"fare_usd":41.8916867348,"ride_type":"premium","city":"Lima","timestamp":"2025-01-01T06:19:00.000"}
{"ride_id":381,"driver_id":1020,"distance_km":24.034394049,"fare_usd":62.814453606,"ride_type":"standard","city":"Nairobi","timestamp":"2025-01-01T06:20:00.000"}
{"ride_id":382,"driver_id":1031,"distance_km":4.0942782533,"fare_usd":25.8862101693,"ride_type":"premium","city":"Lima","timestamp":"2025-01-01T06:21:00.000"}
{"ride_id":383,"driver_id":1022,"distance_km":25.6710963405,"fare_usd":63.7963015271,"ride_type":"pool","city":"Nairobi","timestamp":"2025-01-01T06:22:00.000"}
{"ride_id":384,"driver_id":1032,"distance_km":22.6332612409,"fare_usd":59.0975946012,"ride_type":"pool","city":"Seoul","timestamp":"2025-01-01T06:23:00.000"}
{"ride_id":385,"driver_id":1002,"distance_km":12.8470304951,"fare_usd":21.1037578122,"ride_type":"standard","city":"Nairobi","timestamp":"2025-01-01T06:24:00.000"}
{"ride_id":386,"driver_id":1017,"distance_km":28.0552039459,"fare_usd":14.1934588487,"ride_type":"premium","city":"Seoul","timestamp":"2025-01-01T06:25:00.000"}
{"ride_id":387,"driver_id":1024,"distance_km":29.7369548173,"fare_usd":65.7638025773,"ride_type":"pool","city":"Nairobi","timestamp":"2025-01-01T06:26:00.000"}
{"ride_id":388,"driver_id":1041,"distance_km":6.9450524915,"fare_usd":72.4265657408,"ride_type":"premium","city":"Lima","timestamp":"2025-01-01T06:27:00.000"}
{"ride_id":389,"driver_id":1030,"distance_km":11.997628964,"fare_usd":7.1911619623,"ride_type":"premium","city":"Lima","timestamp":"2025-01-01T06:28:00.000"}
{"ride_id":390,"driver_id":1002,"distance_km":27.8670332841,"fare_usd":56.1889046882,"ride_type":"standard","city":"Lima","timestamp":"2025-01-01T06:29:00.000"}
{"ride_id":391,"driver_id":1039,"distance_km":21.9262999718,"fare_usd":68.6667157663,"ride_type":"pool","city":"Toronto","timestamp":"2025-01-01T06:30:00.000"}
{"ride_id":392,"driver_id":1045,"distance_km":2.394744675,"fare_usd":65.0152064465,"ride_type":"standard","city":"Berlin","timestamp":"2025-01-01T06:31:00.000"}
{"ride_id":393,"driver_id":1023,"distance_km":23.6639199708,"fare_usd":72.5164330589,"ride_type":"standard","city":"Lima","timestamp":"2025-01-01T06:32:00.000"}
{"ride_id":394,"driver_id":1049,"distance_km":25.0102857281,"fare_usd":58.2065854907,"ride_type":"pool","city":"Seoul","timestamp":"2025-01-01T06:33:00.000"}
{"ride_id":395,"driver_id":1031,"distance_km":22.7645558182,"fare_usd":35.9609133667,"ride_type":"pool","city":"Lima","timestamp":"2025-01-01T06:34:00.000"}
{"ride_id":396,"driver_id":1046,"distance_km":24.1865767967,"fare_usd":26.8366393347,"ride_type":"premium","city":"Toronto","timestamp":"2025-01-01T06:35:00.000"}
{"ride_id":397,"driver_id":1021,"distance_km":24.9288476241,"fare_usd":27.4519918307,"ride_type":"pool","city":"Seoul","timestamp":"2025-01-01T06:36:00.000"}
{"ride_id":398,"driver_id":1022,"distance_km":6.4057446169,"fare_usd":55.709587083,"ride_type":"premium","city":"Toronto","timestamp":"2025-01-01T06:37:00.000"}
{"ride_id":399,"driver_id":1001,"distance_km":7.8350606359,"fare_usd":57.2085908422,"ride_type":"premium","city":"Seoul","timestamp":"2025-01-01T06:38:00.000"}
{"ride_id":400,"driver_id":1026,"distance_km":19.3789983479,"fare_usd":19.0251400484,"ride_type":"premium","city":"Nairobi","timestamp":"2025-01-01T06:39:00.000"}
{"ride_id":401,"driver_id":1041,"distance_km":27.3281177834,"fare_usd":65.7685969443,"ride_type":"pool","city":"Berlin","timestamp":"2025-01-01T06:40:00.000"}
{"ride_id":402,"driver_id":1001,"distance_km":10.1697008866,"fare_usd":55.0446828142,"ride_type":"standard","city":"Berlin","timestamp":"2025-01-01T06:41:00.000"}
{"ride_id":403,"driver_id":1025,"distance_km":18.0608935981,"fare_usd":44.392520044,"ride_type":"premium","city":"Toronto","timestamp":"2025-01-01T06:42:00.000"}
{"ride_id":404,"driver_id":1016,"distance_km":20.8064798391,"fare_usd":38.0072722072,"ride_type":"standard","city":"Berlin","timestamp":"2025-01-01T06:43:00.000"}
{"ride_id":405,"driver_id":1039,"distance_km":14.1065094377,"fare_usd":43.0262964053,"ride_type":"standard","city":"Toronto","timestamp":"2025-01-01T06:44:00.000"}
{"ride_id":406,"driver_id":1032,"distance_km":21.6996911908,"fare_usd":16.1472016795,"ride_type":"pool","city":"Toronto","timestamp":"2025-01-01T06:45:00.000"}
{"ride_id":407,"driver_id":1008,"distance_km":27.0903559135,"fare_usd":19.2590874493,"ride_type":"standard","city":"Toronto","timestamp":"2025-01-01T06:46:00.000"}
{"ride_id":408,"driver_id":1042,"distance_km":19.0989447813,"fare_usd":11.3815143284,"ride_type":"standard","city":"Berlin","timestamp":"2025-01-01T06:47:00.000"}
{"ride_id":409,"driver_id":1047,"distance_km":16.6536507955,"fare_usd":15.7560626713,"ride_type":"pool","city":"Toronto","timestamp":"2025-01-01T06:48:00.000"}
{"ride_id":410,"driver_id":1038,"distance_km":13.7235955863,"fare_usd":36.7585544224,"ride_type":"premium","city":"Berlin","timestamp":"2025-01-01T06:49:00.000"}
{"ride_id":411,"driver_id":1028,"distance_km":17.7471018563,"fare_usd":42.124807561,"ride_type":"standard","city":"Toronto","timestamp":"2025-01-01T06:50:00.000"}
{"ride_id":412,"driver_id":1041,"distance_km":11.3055111027,"fare_usd":6.2503324735,"ride_type":"pool","city":"Lima","timestamp":"2025-01-01T06:51:00.000"}
{"ride_id":413,"driver_id":1025,"distance_km":12.3529811958,"fare_usd":60.7758479505,"ride_type":"standard","city":"Toronto","timestamp":"2025-01-01T06:52:00.000"}
{"ride_id":414,"driver_id":1034,"distance_km":16.423866911,"fare_usd":25.591758134,"ride_type":"standard","city":"Seoul","timestamp":"2025-01-01T06:53:00.000"}
{"ride_id":415,"driver_id":1049,"distance_km":2.9319542593,"fare_usd":68.8285224472,"ride_type":"premium","city":"Toronto","timestamp":"2025-01-01T06:54:00.000"}
{"ride_id":416,"driver_id":1024,"distance_km":7.6417363368,"fare_usd":72.725788453,"ride_type":"standard","city":"Nairobi","timestamp":"2025-01-01T06:55:00.000"}
{"ride_id":417,"driver_id":1023,"distance_km":16.7426300078,"fare_usd":17.9821212274,"ride_type":"pool","city":"Toronto","timestamp":"2025-01-01T06:56:00.000"}
{"ride_id":418,"driver_id":1012,"distance_km":13.514316151,"fare_usd":37.3468103536,"ride_type":"standard","city":"Seoul","timestamp":"2025-01-01T06:57:00.000"}
{"ride_id":419,"driver_id":1006,"distance_km":10.6516577915,"fare_usd":5.0862284616,"ride_type":"premium","city":"Seoul","timestamp":"2025-01-01T06:58:00.000"}
{"ride_id":420,"driver_id":1035,"distance_km":22.1859249675,"fare_usd":46.8829085586,"ride_type":"premium","city":"Berlin","timestamp":"2025-01-01T06:59:00.000"}
{"ride_id":421,"driver_id":1044,"distance_km":21.1178106147,"fare_usd":47.5114513784,"ride_type":"pool","city":"Lima","timestamp":"2025-01-01T07:00:00.000"}
{"ride_id":422,"driver_id":1019,"distance_km":5.8351920398,"fare_usd":22.3277968922,"ride_type":"premium","city":"Toronto","timestamp":"2025-01-01T07:01:00.000"}
{"ride_id":423,"driver_id":1000,"distance_km":26.4802443458,"fare_usd":44.0888870808,"ride_type":"standard","city":"Berlin","timestamp":"2025-01-01T07:02:00.000"}
{"ride_id":424,"driver_id":1007,"distance_km":15.3672851657,"fare_usd":20.7878099711,"ride_type":"premium","city":"Lima","timestamp":"2025-01-01T07:03:00.000"}
{"ride_id":425,"driver_id":1045,"distance_km":22.502366423,"fare_usd":16.2577828355,"ride_type":"pool","city":"Toronto","timestamp":"2025-01-01T07:04:00.000"}
{"ride_id":426,"driver_id":1015,"distance_km":17.6213746285,"fare_usd":50.6063626762,"ride_type":"premium","city":"Nairobi","timestamp":"2025-01-01T07:05:00.000"}
{"ride_id":427,"driver_id":1013,"distance_km":29.9330858618,"fare_usd":27.8147824766,"ride_type":"premium","city":"Toronto","timestamp":"2025-01-01T07:06:00.000"}
{"ride_id":428,"driver_id":1011,"distance_km":22.8196904811,"fare_usd":46.318475722,"ride_type":"premium","city":"Seoul","timestamp":"2025-01-01T07:07:00.000"}
{"ride_id":429,"driver_id":1050,"distance_km":21.5024333761,"fare_usd":35.327272428,"ride_type":"pool","city":"Seoul","timestamp":"2025-01-01T07:08:00.000"}
{"ride_id":430,"driver_id":1022,"distance_km":23.5785862325,"fare_usd":73.9045985182,"ride_type":"premium","city":"Nairobi","timestamp":"2025-01-01T07:09:00.000"}
{"ride_id":431,"driver_id":1014,"distance_km":5.1507115809,"fare_usd":15.4706449867,"ride_type":"premium","city":"Berlin","timestamp":"2025-01-01T07:10:00.000"}
{"ride_id":432,"driver_id":1027,"distance_km":6.9317932019,"fare_usd":37.5219017645,"ride_type":"standard","city":"Lima","timestamp":"2025-01-01T07:11:00.000"}
{"ride_id":433,"driver_id":1033,"distance_km":21.7078583845,"fare_usd":52.6319638452,"ride_type":"pool","city":"Toronto","timestamp":"2025-01-01T07:12:00.000"}
{"ride_id":434,"driver_id":1001,"distance_km":15.3254631268,"fare_usd":32.6881558716,"ride_type":"premium","city":"Seoul","timestamp":"2025-01-01T07:13:00.000"}
{"ride_id":435,"driver_id":1031,"distance_km":22.8844234639,"fare_usd":73.2289896309,"ride_type":"pool","city":"Berlin","timestamp":"2025-01-01T07:14:00.000"}
{"ride_id":436,"driver_id":1022,"distance_km":3.9845648916,"fare_usd":55.5321339549,"ride_type":"premium","city":"Nairobi","timestamp":"2025-01-01T07:15:00.000"}
{"ride_id":437,"driver_id":1021,"distance_km":16.5579591931,"fare_usd":50.9888700295,"ride_type":"premium","city":"Seoul","timestamp":"2025-01-01T07:16:00.000"}
{"ride_id":438,"driver_id":1050,"distance_km":11.9858254012,"fare_usd":57.9941487328,"ride_type":"premium","city":"Nairobi","timestamp":"2025-01-01T07:17:00.000"}
{"ride_id":439,"driver_id":1024,"distance_km":14.2530063592,"fare_usd":71.6854046627,"ride_type":"standard","city":"Toronto","timestamp":"2025-01-01T07:18:00.000"}
{"ride_id":440,"driver_id":1021,"distance_km":18.5147782901,"fare_usd":68.5473057089,"ride_type":"standard","city":"Lima","timestamp":"2025-01-01T07:19:00.000"}
{"ride_id":441,"driver_id":1021,"distance_km":15.5663620764,"fare_usd":55.6999715688,"ride_type":"standard","city":"Seoul","timestamp":"2025-01-01T07:20:00.000"}
{"ride_id":442,"driver_id":1048,"distance_km":16.6559584763,"fare_usd":57.4413147371,"ride_type":"pool","city":"Seoul","timestamp":"2025-01-01T07:21:00.000"}
{"ride_id":443,"driver_id":1041,"distance_km":15.1043669779,"fare_usd":15.2145451825,"ride_type":"pool","city":"Toronto","timestamp":"2025-01-01T07:22:00.000"}
{"ride_id":444,"driver_id":1005,"distance_km":12.8597001355,"fare_usd":12.1954683145,"ride_type":"standard","city":"Berlin","timestamp":"2025-01-01T07:23:00.000"}
{"ride_id":445,"driver_id":1014,"distance_km":23.3845774373,"fare_usd":44.9633151291,"ride_type":"pool","city":"Lima","timestamp":"2025-01-01T07:24:00.000"}
{"ride_id":446,"driver_id":1042,"distance_km":1.3538890972,"fare_usd":6.2857345858,"ride_type":"premium","city":"Seoul","timestamp":"2025-01-01T07:25:00.000"}
{"ride_id":447,"driver_id":1036,"distance_km":18.354838335,"fare_usd":38.7649467086,"ride_type":"premium","city":"Lima","timestamp":"2025-01-01T07:26:00.000"}
{"ride_id":448,"driver_id":1032,"distance_km":17.3997420724,"fare_usd":19.7244705943,"ride_type":"premium","city":"Seoul","timestamp":"2025-01-01T07:27:00.000"}
{"ride_id":449,"driver_id":1007,"distance_km":21.7691931673,"fare_usd":29.2211597351,"ride_type":"standard","city":"Lima","timestamp":"2025-01-01T07:28:00.000"}
{"ride_id":450,"driver_id":1043,"distance_km":18.3718515785,"fare_usd":59.3063315055,"ride_type":"pool","city":"Nairobi","timestamp":"2025-01-01T07:29:00.000"}
{"ride_id":451,"driver_id":1043,"distance_km":24.9771660065,"fare_usd":70.8866252963,"ride_type":"standard","city":"Seoul","timestamp":"2025-01-01T07:30:00.000"}
{"ride_id":452,"driver_id":1004,"distance_km":28.8131690424,"fare_usd":10.0691390502,"ride_type":"pool","city":"Lima","timestamp":"2025-01-01T07:31:00.000"}
{"ride_id":453,"driver_id":1038,"distance_km":10.9332034582,"fare_usd":42.3969544184,"ride_type":"premium","city":"Berlin","timestamp":"2025-01-01T07:32:00.000"}
{"ride_id":454,"driver_id":1003,"distance_km":7.5931785079,"fare_usd":66.7773440074,"ride_type":"standard","city":"Nairobi","timestamp":"2025-01-01T07:33:00.000"}
{"ride_id":455,"driver_id":1005,"distance_km":13.2843090102,"fare_usd":10.7755974108,"ride_type":"pool","city":"Nairobi","timestamp":"2025-01-01T07:34:00.000"}
{"ride_id":456,"driver_id":1044,"distance_km":9.3499588778,"fare_usd":62.7159832828,"ride_type":"pool","city":"Berlin","timestamp":"2025-01-01T07:35:00.000"}
{"ride_id":457,"driver_id":1031,"distance_km":18.8335576314,"fare_usd":30.046094565,"ride_type":"premium","city":"Lima","timestamp":"2025-01-01T07:36:00.000"}
{"ride_id":458,"driver_id":1029,"distance_km":27.4437198564,"fare_usd":27.5466291554,"ride_type":"standard","city":"Toronto","timestamp":"2025-01-01T07:37:00.000"}
{"ride_id":459,"driver_id":1046,"distance_km":5.0343696301,"fare_usd":73.422647042,"ride_type":"standard","city":"Berlin","timestamp":"2025-01-01T07:38:00.000"}
{"ride_id":460,"driver_id":1034,"distance_km":3.9230434875,"fare_usd":19.0601362904,"ride_type":"standard","city":"Lima","timestamp":"2025-01-01T07:39:00.000"}
{"ride_id":461,"driver_id":1039,"distance_km":8.4244504238,"fare_usd":53.5235758576,"ride_type":"premium","city":"Berlin","timestamp":"2025-01-01T07:40:00.000"}
{"ride_id":462,"driver_id":1015,"distance_km":22.0567719958,"fare_usd":62.5008509607,"ride_type":"standard","city":"Berlin","timestamp":"2025-01-01T07:41:00.000"}
{"ride_id":463,"driver_id":1012,"distance_km":18.1959242525,"fare_usd":7.8828446695,"ride_type":"premium","city":"Seoul","timestamp":"2025-01-01T07:42:00.000"}
{"ride_id":464,"driver_id":1049,"distance_km":3.9641672625,"fare_usd":51.9269820848,"ride_type":"premium","city":"Lima","timestamp":"2025-01-01T07:43:00.000"}
{"ride_id":465,"driver_id":1041,"distance_km":27.6437651456,"fare_usd":71.6084982049,"ride_type":"premium","city":"Toronto","timestamp":"2025-01-01T07:44:00.000"}
{"ride_id":466,"driver_id":1029,"distance_km":23.9124544766,"fare_usd":13.695397671,"ride_type":"pool","city":"Seoul","timestamp":"2025-01-01T07:45:00.000"}
{"ride_id":467,"driver_id":1018,"distance_km":1.6676555388,"fare_usd":67.735491188,"ride_type":"standard","city":"Berlin","timestamp":"2025-01-01T07:46:00.000"}
{"ride_id":468,"driver_id":1016,"distance_km":19.8896491187,"fare_usd":46.6343646164,"ride_type":"standard","city":"Berlin","timestamp":"2025-01-01T07:47:00.000"}
{"ride_id":469,"driver_id":1018,"distance_km":23.3661533871,"fare_usd":48.1623207304,"ride_type":"premium","city":"Berlin","timestamp":"2025-01-01T07:48:00.000"}
{"ride_id":470,"driver_id":1027,"distance_km":11.8586257219,"fare_usd":47.9060922406,"ride_type":"premium","city":"Lima","timestamp":"2025-01-01T07:49:00.000"}
{"ride_id":471,"driver_id":1025,"distance_km":2.9987246416,"fare_usd":25.9185120436,"ride_type":"standard","city":"Lima","timestamp":"2025-01-01T07:50:00.000"}
{"ride_id":472,"driver_id":1036,"distance_km":3.2423108992,"fare_usd":70.464127071,"ride_type":"premium","city":"Seoul","timestamp":"2025-01-01T07:51:00.000"}
{"ride_id":473,"driver_id":1025,"distance_km":4.0231620155,"fare_usd":71.3145323842,"ride_type":"standard","city":"Toronto","timestamp":"2025-01-01T07:52:00.000"}
{"ride_id":474,"driver_id":1022,"distance_km":25.3727493274,"fare_usd":48.771326215,"ride_type":"pool","city":"Seoul","timestamp":"2025-01-01T07:53:00.000"}
{"ride_id":475,"driver_id":1008,"distance_km":27.4098997494,"fare_usd":59.8395908159,"ride_type":"premium","city":"Nairobi","timestamp":"2025-01-01T07:54:00.000"}
{"ride_id":476,"driver_id":1011,"distance_km":4.5615126735,"fare_usd":47.8580590117,"ride_type":"standard","city":"Berlin","timestamp":"2025-01-01T07:55:00.000"}
{"ride_id":477,"driver_id":1000,"distance_km":7.8412750033,"fare_usd":38.9078913302,"ride_type":"premium","city":"Berlin","timestamp":"2025-01-01T07:56:00.000"}
{"ride_id":478,"driver_id":1000,"distance_km":5.8000948007,"fare_usd":51.2574082809,"ride_type":"standard","city":"Berlin","timestamp":"2025-01-01T07:57:00.000"}
{"ride_id":479,"driver_id":1046,"distance_km":6.4033055053,"fare_usd":43.7101016814,"ride_type":"standard","city":"Seoul","timestamp":"2025-01-01T07:58:00.000"}
{"ride_id":480,"driver_id":1033,"distance_km":25.2872328811,"fare_usd":46.8233103842,"ride_type":"premium","city":"Seoul","timestamp":"2025-01-01T07:59:00.000"}
{"ride_id":481,"driver_id":1031,"distance_km":10.632245967,"fare_usd":59.8682787393,"ride_type":"pool","city":"Berlin","timestamp":"2025-01-01T08:00:00.000"}
{"ride_id":482,"driver_id":1047,"distance_km":10.0318836573,"fare_usd":38.6632682014,"ride_type":"standard","city":"Seoul","timestamp":"2025-01-01T08:01:00.000"}
{"ride_id":483,"driver_id":1024,"distance_km":7.5944730054,"fare_usd":7.8527874265,"ride_type":"standard","city":"Lima","timestamp":"2025-01-01T08:02:00.000"}
{"ride_id":484,"driver_id":1039,"distance_km":18.62893742,"fare_usd":16.4799636693,"ride_type":"standard","city":"Lima","timestamp":"2025-01-01T08:03:00.000"}
{"ride_id":485,"driver_id":1044,"distance_km":11.9998652532,"fare_usd":35.7025051543,"ride_type":"pool","city":"Seoul","timestamp":"2025-01-01T08:04:00.000"}
{"ride_id":486,"driver_id":1000,"distance_km":22.5832399035,"fare_usd":55.7378591912,"ride_type":"pool","city":"Berlin","timestamp":"2025-01-01T08:05:00.000"}
{"ride_id":487,"driver_id":1015,"distance_km":6.9618144429,"fare_usd":46.5295053817,"ride_type":"premium","city":"Seoul","timestamp":"2025-01-01T08:06:00.000"}
{"ride_id":488,"driver_id":1038,"distance_km":23.8459067727,"fare_usd":50.5205930111,"ride_type":"pool","city":"Seoul","timestamp":"2025-01-01T08:07:00.000"}
{"ride_id":489,"driver_id":1004,"distance_km":18.5079244202,"fare_usd":38.5495250003,"ride_type":"premium","city":"Seoul","timestamp":"2025-01-01T08:08:00.000"}
{"ride_id":490,"driver_id":1021,"distance_km":4.3137517016,"fare_usd":48.101941536,"ride_type":"premium","city":"Nairobi","timestamp":"2025-01-01T08:09:00.000"}
{"ride_id":491,"driver_id":1028,"distance_km":13.0206329419,"fare_usd":28.031220647,"ride_type":"pool","city":"Lima","timestamp":"2025-01-01T08:10:00.000"}
{"ride_id":492,"driver_id":1002,"distance_km":26.0420260778,"fare_usd":37.9127814888,"ride_type":"premium","city":"Toronto","timestamp":"2025-01-01T08:11:00.000"}
{"ride_id":493,"driver_id":1011,"distance_km":27.7658467222,"fare_usd":57.0995345916,"ride_type":"pool","city":"Toronto","timestamp":"2025-01-01T08:12:00.000"}
{"ride_id":494,"driver_id":1025,"distance_km":14.5053035472,"fare_usd":66.0282945281,"ride_type":"premium","city":"Nairobi","timestamp":"2025-01-01T08:13:00.000"}
{"ride_id":495,"driver_id":1015,"distance_km":14.9442723646,"fare_usd":35.3558733769,"ride_type":"pool","city":"Seoul","timestamp":"2025-01-01T08:14:00.000"}
{"ride_id":496,"driver_id":1050,"distance_km":27.6351870232,"fare_usd":8.0563160395,"ride_type":"pool","city":"Nairobi","timestamp":"2025-01-01T08:15:00.000"}
{"ride_id":497,"driver_id":1036,"distance_km":18.0249785,"fare_usd":16.3170780903,"ride_type":"premium","city":"Nairobi","timestamp":"2025-01-01T08:16:00.000"}
{"ride_id":498,"driver_id":1021,"distance_km":1.9525534371,"fare_usd":6.4602797504,"ride_type":"standard","city":"Berlin","timestamp":"2025-01-01T08:17:00.000"}
{"ride_id":499,"driver_id":1028,"distance_km":27.4697344235,"fare_usd":50.7284113466,"ride_type":"premium","city":"Lima","timestamp":"2025-01-01T08:18:00.000"}
{"ride_id":500,"driver_id":1013,"distance_km":8.19856684,"fare_usd":28.2620237749,"ride_type":"pool","city":"Toronto","timestamp":"2025-01-01T08:19:00.000"}
